{
"bones": [
	{ "name": "root" },
	{ "name": "ball", "parent": "root" },
	{ "name": "ball2", "parent": "root" },
	{ "name": "cloud01", "parent": "root", "x": -24.56, "y": -1.08, "scaleX": 0.47, "scaleY": 0.47 },
	{ "name": "cloud02", "parent": "root", "x": 14.01, "y": -10.09, "scaleX": 0.52, "scaleY": 0.52 },
	{ "name": "cloud03", "parent": "root", "x": 9.51, "y": 31.7, "scaleX": 0.47, "scaleY": 0.47 },
	{ "name": "cloud04", "parent": "root", "x": 9.51, "y": -33.23, "scaleX": 0.47, "scaleY": 0.47 },
	{ "name": "cloud05", "parent": "root", "x": 9.51, "y": 19.48, "scaleX": 0.47, "scaleY": 0.47 },
	{ "name": "star01", "parent": "root", "x": -34.2, "y": 40.7 },
	{ "name": "star02", "parent": "root", "x": 44.23, "y": -13.94 },
	{ "name": "star03", "parent": "root", "x": 23.66, "y": 32.99 },
	{ "name": "star04", "parent": "root", "x": -21.34, "y": -53.81 },
	{ "name": "ring", "parent": "ball" }
],
"slots": [
	{ "name": "ring", "bone": "ring", "attachment": "ring" },
	{ "name": "ball", "bone": "ball", "attachment": "ball" },
	{ "name": "ball2", "bone": "ball2", "attachment": "ball", "additive": true },
	{ "name": "star", "bone": "star01", "color": "ffffff00", "attachment": "star" },
	{ "name": "star2", "bone": "star02", "color": "ffffff00", "attachment": "star" },
	{ "name": "star22", "bone": "star03", "color": "ffffff00", "attachment": "star" },
	{ "name": "star222", "bone": "star04", "color": "ffffff00", "attachment": "star" },
	{ "name": "cloud", "bone": "cloud01", "color": "ffffff00", "attachment": "cloud", "additive": true },
	{ "name": "cloud3", "bone": "cloud03", "color": "ffffff00", "attachment": "cloud", "additive": true },
	{ "name": "cloud32", "bone": "cloud04", "color": "ffffff00", "attachment": "cloud", "additive": true },
	{ "name": "cloud322", "bone": "cloud05", "color": "ffffff00", "attachment": "cloud", "additive": true },
	{ "name": "cloud2", "bone": "cloud02", "color": "ffffff00", "attachment": "cloud", "additive": true }
],
"skins": {
	"default": {
		"ball": {
			"ball": { "width": 140, "height": 140 }
		},
		"ball2": {
			"ball": { "width": 140, "height": 140 }
		},
		"cloud": {
			"cloud": { "width": 130, "height": 122 }
		},
		"cloud2": {
			"cloud": { "width": 130, "height": 122 }
		},
		"cloud3": {
			"cloud": { "width": 130, "height": 122 }
		},
		"cloud32": {
			"cloud": { "width": 130, "height": 122 }
		},
		"cloud322": {
			"cloud": { "width": 130, "height": 122 }
		},
		"ring": {
			"ring": { "width": 235, "height": 229 }
		},
		"star": {
			"star": { "width": 29, "height": 29 }
		},
		"star2": {
			"star": { "width": 29, "height": 29 }
		},
		"star22": {
			"star": { "width": 29, "height": 29 }
		},
		"star222": {
			"star": { "width": 29, "height": 29 }
		}
	}
},
"animations": {
	"animation1": {
		"slots": {
			"ball": {
				"attachment": [
					{ "time": 0, "name": "ball" },
					{ "time": 0.5, "name": "ball" }
				],
				"color": [
					{ "time": 0, "color": "ffffff00", "curve": "stepped" },
					{ "time": 0.5, "color": "ffffff00" }
				]
			},
			"ball2": {
				"attachment": [
					{ "time": 0, "name": "ball" },
					{ "time": 0.5, "name": "ball" }
				],
				"color": [
					{ "time": 0, "color": "ffffff00", "curve": "stepped" },
					{ "time": 0.5, "color": "ffffff00" }
				]
			},
			"cloud": {
				"attachment": [
					{ "time": 0, "name": "cloud" },
					{ "time": 0.4, "name": "cloud" },
					{ "time": 0.5, "name": "cloud" }
				],
				"color": [
					{ "time": 0, "color": "ffffff00" },
					{ "time": 0.1, "color": "ffffffff" },
					{ "time": 0.3666, "color": "ffffff00", "curve": "stepped" },
					{ "time": 0.5, "color": "ffffff00" }
				]
			},
			"cloud2": {
				"attachment": [
					{ "time": 0, "name": "cloud" },
					{ "time": 0.1, "name": "cloud" },
					{ "time": 0.4, "name": "cloud" },
					{ "time": 0.5, "name": "cloud" }
				],
				"color": [
					{ "time": 0, "color": "ffffff00", "curve": "stepped" },
					{ "time": 0.0666, "color": "ffffff00" },
					{ "time": 0.1, "color": "ffffffff" },
					{ "time": 0.3666, "color": "ffffff00", "curve": "stepped" },
					{ "time": 0.5, "color": "ffffff00" }
				]
			},
			"cloud3": {
				"attachment": [
					{ "time": 0, "name": "cloud" },
					{ "time": 0.4, "name": "cloud" },
					{ "time": 0.5, "name": "cloud" }
				],
				"color": [
					{ "time": 0, "color": "ffffff00" },
					{ "time": 0.0333, "color": "ffffffff" },
					{ "time": 0.3, "color": "ffffff00", "curve": "stepped" },
					{ "time": 0.5, "color": "ffffff00" }
				]
			},
			"cloud32": {
				"attachment": [
					{ "time": 0, "name": "cloud" },
					{ "time": 0.4, "name": "cloud" },
					{ "time": 0.5, "name": "cloud" }
				],
				"color": [
					{ "time": 0, "color": "ffffff00", "curve": "stepped" },
					{ "time": 0.0333, "color": "ffffff00" },
					{ "time": 0.0666, "color": "ffffffff" },
					{ "time": 0.3333, "color": "ffffff00", "curve": "stepped" },
					{ "time": 0.5, "color": "ffffff00" }
				]
			},
			"cloud322": {
				"attachment": [
					{ "time": 0, "name": "cloud" },
					{ "time": 0.4, "name": "cloud" },
					{ "time": 0.5, "name": "cloud" }
				],
				"color": [
					{ "time": 0, "color": "ffffff00", "curve": "stepped" },
					{ "time": 0.4, "color": "ffffff00", "curve": "stepped" },
					{ "time": 0.5, "color": "ffffff00" }
				]
			},
			"ring": {
				"attachment": [
					{ "time": 0, "name": "ring" },
					{ "time": 0.5, "name": "ring" }
				],
				"color": [
					{ "time": 0, "color": "ffffffff", "curve": "stepped" },
					{ "time": 0.5, "color": "ffffffff" }
				]
			},
			"star": {
				"attachment": [
					{ "time": 0, "name": "star" },
					{ "time": 0.4, "name": "star" },
					{ "time": 0.5, "name": "star" }
				],
				"color": [
					{ "time": 0, "color": "ffffff00" },
					{ "time": 0.0333, "color": "ffffffff" },
					{ "time": 0.3, "color": "ffffff00", "curve": "stepped" },
					{ "time": 0.5, "color": "ffffff00" }
				]
			},
			"star2": {
				"attachment": [
					{ "time": 0, "name": "star" },
					{ "time": 0.4, "name": "star" },
					{ "time": 0.5, "name": "star" }
				],
				"color": [
					{ "time": 0, "color": "ffffff00", "curve": "stepped" },
					{ "time": 0.0666, "color": "ffffff00" },
					{ "time": 0.1, "color": "ffffffff" },
					{ "time": 0.3333, "color": "ffffff00", "curve": "stepped" },
					{ "time": 0.5, "color": "ffffff00" }
				]
			},
			"star22": {
				"attachment": [
					{ "time": 0, "name": "star" },
					{ "time": 0.4, "name": "star" },
					{ "time": 0.5, "name": "star" }
				],
				"color": [
					{ "time": 0, "color": "ffffff00", "curve": "stepped" },
					{ "time": 0.1, "color": "ffffff00" },
					{ "time": 0.1333, "color": "ffffffff" },
					{ "time": 0.3666, "color": "ffffff00", "curve": "stepped" },
					{ "time": 0.5, "color": "ffffff00" }
				]
			},
			"star222": {
				"attachment": [
					{ "time": 0, "name": "star" },
					{ "time": 0.4, "name": "star" },
					{ "time": 0.5, "name": "star" }
				],
				"color": [
					{ "time": 0, "color": "ffffff00", "curve": "stepped" },
					{ "time": 0.1333, "color": "ffffff00" },
					{ "time": 0.1666, "color": "ffffffff" },
					{ "time": 0.4, "color": "ffffff00", "curve": "stepped" },
					{ "time": 0.5, "color": "ffffff00" }
				]
			}
		},
		"bones": {
			"ball2": {
				"rotate": [
					{ "time": 0, "angle": 0, "curve": "stepped" },
					{ "time": 0.5, "angle": 0 }
				],
				"translate": [
					{ "time": 0, "x": 0, "y": 0, "curve": "stepped" },
					{ "time": 0.5, "x": 0, "y": 0 }
				],
				"scale": [
					{ "time": 0, "x": 1, "y": 1, "curve": "stepped" },
					{ "time": 0.5, "x": 1, "y": 1 }
				]
			},
			"root": {
				"rotate": [
					{ "time": 0, "angle": 0, "curve": "stepped" },
					{ "time": 0.5, "angle": 0 }
				],
				"translate": [
					{ "time": 0, "x": 0, "y": 0, "curve": "stepped" },
					{ "time": 0.5, "x": 0, "y": 0 }
				],
				"scale": [
					{ "time": 0, "x": 1, "y": 1, "curve": "stepped" },
					{ "time": 0.5, "x": 1, "y": 1 }
				]
			},
			"ball": {
				"rotate": [
					{ "time": 0, "angle": 0, "curve": "stepped" },
					{ "time": 0.5, "angle": 0 }
				],
				"translate": [
					{ "time": 0, "x": 0, "y": 0, "curve": "stepped" },
					{ "time": 0.5, "x": 0, "y": 0 }
				],
				"scale": [
					{ "time": 0, "x": 1, "y": 1, "curve": "stepped" },
					{ "time": 0.5, "x": 1, "y": 1 }
				]
			},
			"cloud01": {
				"rotate": [
					{ "time": 0, "angle": 0, "curve": "stepped" },
					{ "time": 0.0666, "angle": 0, "curve": "stepped" },
					{ "time": 0.1, "angle": 0, "curve": "stepped" },
					{ "time": 0.4, "angle": 0, "curve": "stepped" },
					{ "time": 0.5, "angle": 0 }
				],
				"translate": [
					{ "time": 0, "x": 0, "y": 0, "curve": "stepped" },
					{ "time": 0.0666, "x": 0, "y": 0, "curve": "stepped" },
					{ "time": 0.1, "x": 0, "y": 0 },
					{ "time": 0.3666, "x": -421.87, "y": 0 },
					{ "time": 0.4, "x": -293.14, "y": 0, "curve": "stepped" },
					{ "time": 0.5, "x": -293.14, "y": 0 }
				],
				"scale": [
					{ "time": 0, "x": 1, "y": 1, "curve": "stepped" },
					{ "time": 0.0666, "x": 1, "y": 1, "curve": "stepped" },
					{ "time": 0.1, "x": 1, "y": 1 },
					{ "time": 0.2333, "x": 1.488, "y": 1.488 },
					{ "time": 0.4, "x": 1, "y": 1, "curve": "stepped" },
					{ "time": 0.5, "x": 1, "y": 1 }
				]
			},
			"cloud02": {
				"rotate": [
					{ "time": 0, "angle": 0, "curve": "stepped" },
					{ "time": 0.1, "angle": 0, "curve": "stepped" },
					{ "time": 0.4, "angle": 0, "curve": "stepped" },
					{ "time": 0.5, "angle": 0 }
				],
				"translate": [
					{ "time": 0, "x": 0, "y": 0 },
					{
						"time": 0.1,
						"x": 0,
						"y": 37.42,
						"curve": [ 0.228, 0.34, 0.421, 0.81 ]
					},
					{
						"time": 0.3666,
						"x": -372.98,
						"y": 45.59,
						"curve": [ 0.309, 0.4, 0.641, 0.73 ]
					},
					{ "time": 0.4333, "x": -670.87, "y": 59.01, "curve": "stepped" },
					{ "time": 0.5, "x": -670.87, "y": 59.01 }
				],
				"scale": [
					{ "time": 0, "x": 1, "y": 1, "curve": "stepped" },
					{ "time": 0.1, "x": 1, "y": 1 },
					{ "time": 0.2666, "x": 1.457, "y": 1.457, "curve": "stepped" },
					{ "time": 0.5, "x": 1.457, "y": 1.457 }
				]
			},
			"cloud03": {
				"rotate": [
					{ "time": 0, "angle": 0, "curve": "stepped" },
					{ "time": 0.0333, "angle": 0, "curve": "stepped" },
					{ "time": 0.4, "angle": 0, "curve": "stepped" },
					{ "time": 0.5, "angle": 0 }
				],
				"translate": [
					{ "time": 0, "x": 0, "y": 0, "curve": "stepped" },
					{ "time": 0.0333, "x": 0, "y": 0 },
					{ "time": 0.3, "x": -552.89, "y": 0 },
					{ "time": 0.4, "x": 0, "y": 0, "curve": "stepped" },
					{ "time": 0.5, "x": 0, "y": 0 }
				],
				"scale": [
					{ "time": 0, "x": 1, "y": 1, "curve": "stepped" },
					{ "time": 0.0333, "x": 1, "y": 1 },
					{ "time": 0.1666, "x": 1.537, "y": 1.537 },
					{ "time": 0.4, "x": 1, "y": 1, "curve": "stepped" },
					{ "time": 0.5, "x": 1, "y": 1 }
				]
			},
			"cloud04": {
				"rotate": [
					{ "time": 0, "angle": 0, "curve": "stepped" },
					{ "time": 0.0666, "angle": 0, "curve": "stepped" },
					{ "time": 0.4, "angle": 0, "curve": "stepped" },
					{ "time": 0.5, "angle": 0 }
				],
				"translate": [
					{ "time": 0, "x": 0, "y": 0, "curve": "stepped" },
					{ "time": 0.0666, "x": 0, "y": 0 },
					{ "time": 0.3333, "x": -479.87, "y": 0 },
					{ "time": 0.4, "x": 0, "y": 0, "curve": "stepped" },
					{ "time": 0.5, "x": 0, "y": 0 }
				],
				"scale": [
					{ "time": 0, "x": 1, "y": 1, "curve": "stepped" },
					{ "time": 0.0666, "x": 1, "y": 1 },
					{ "time": 0.2, "x": 1.499, "y": 1.499 },
					{ "time": 0.4, "x": 1, "y": 1, "curve": "stepped" },
					{ "time": 0.5, "x": 1, "y": 1 }
				]
			},
			"cloud05": {
				"rotate": [
					{ "time": 0, "angle": 0, "curve": "stepped" },
					{ "time": 0.4, "angle": 0, "curve": "stepped" },
					{ "time": 0.5, "angle": 0 }
				],
				"translate": [
					{ "time": 0, "x": 0, "y": 0 },
					{ "time": 0.1, "x": 0, "y": -66.03, "curve": "stepped" },
					{ "time": 0.5, "x": 0, "y": -66.03 }
				],
				"scale": [
					{ "time": 0, "x": 1, "y": 1, "curve": "stepped" },
					{ "time": 0.4, "x": 1, "y": 1, "curve": "stepped" },
					{ "time": 0.5, "x": 1, "y": 1 }
				]
			},
			"star01": {
				"rotate": [
					{ "time": 0, "angle": 0, "curve": "stepped" },
					{ "time": 0.0333, "angle": 0, "curve": "stepped" },
					{ "time": 0.4, "angle": 0, "curve": "stepped" },
					{ "time": 0.5, "angle": 0 }
				],
				"translate": [
					{ "time": 0, "x": 0, "y": 0 },
					{
						"time": 0.0333,
						"x": 5.36,
						"y": 0,
						"curve": [ 0.384, 0.24, 0.715, 0.4 ]
					},
					{ "time": 0.3, "x": -602.06, "y": 0 },
					{ "time": 0.4, "x": 0, "y": 0, "curve": "stepped" },
					{ "time": 0.5, "x": 0, "y": 0 }
				],
				"scale": [
					{ "time": 0, "x": 1, "y": 1, "curve": "stepped" },
					{ "time": 0.0333, "x": 1, "y": 1, "curve": "stepped" },
					{ "time": 0.4, "x": 1, "y": 1, "curve": "stepped" },
					{ "time": 0.5, "x": 1, "y": 1 }
				]
			},
			"star02": {
				"rotate": [
					{ "time": 0, "angle": 0, "curve": "stepped" },
					{ "time": 0.0666, "angle": 0, "curve": "stepped" },
					{ "time": 0.4, "angle": 0, "curve": "stepped" },
					{ "time": 0.5, "angle": 0 }
				],
				"translate": [
					{ "time": 0, "x": 0, "y": 0, "curve": "stepped" },
					{
						"time": 0.0666,
						"x": 0,
						"y": 0,
						"curve": [ 0.25, 0, 0.712, 0.58 ]
					},
					{ "time": 0.3333, "x": -514.06, "y": 0 },
					{ "time": 0.4, "x": 0, "y": 0, "curve": "stepped" },
					{ "time": 0.5, "x": 0, "y": 0 }
				],
				"scale": [
					{ "time": 0, "x": 1, "y": 1 },
					{ "time": 0.0666, "x": 1.488, "y": 1.488 },
					{ "time": 0.1, "x": 1.861, "y": 1.861 },
					{ "time": 0.4, "x": 1, "y": 1, "curve": "stepped" },
					{ "time": 0.5, "x": 1, "y": 1 }
				]
			},
			"star03": {
				"rotate": [
					{ "time": 0, "angle": 0, "curve": "stepped" },
					{ "time": 0.1, "angle": 0, "curve": "stepped" },
					{ "time": 0.1333, "angle": 0, "curve": "stepped" },
					{ "time": 0.4, "angle": 0, "curve": "stepped" },
					{ "time": 0.5, "angle": 0 }
				],
				"translate": [
					{ "time": 0, "x": 0, "y": 0, "curve": "stepped" },
					{ "time": 0.1, "x": 0, "y": 0, "curve": "stepped" },
					{
						"time": 0.1333,
						"x": 0,
						"y": 0,
						"curve": [ 0.25, 0, 0.767, 0.4 ]
					},
					{ "time": 0.3666, "x": -560.12, "y": 0 },
					{ "time": 0.4, "x": 0, "y": 0, "curve": "stepped" },
					{ "time": 0.5, "x": 0, "y": 0 }
				],
				"scale": [
					{ "time": 0, "x": 1, "y": 1, "curve": "stepped" },
					{ "time": 0.1, "x": 1, "y": 1 },
					{ "time": 0.1333, "x": 1.633, "y": 1.633 },
					{ "time": 0.4, "x": 1, "y": 1, "curve": "stepped" },
					{ "time": 0.5, "x": 1, "y": 1 }
				]
			},
			"star04": {
				"rotate": [
					{ "time": 0, "angle": 0, "curve": "stepped" },
					{ "time": 0.1666, "angle": 0, "curve": "stepped" },
					{ "time": 0.4, "angle": 0, "curve": "stepped" },
					{ "time": 0.5, "angle": 0 }
				],
				"translate": [
					{ "time": 0, "x": 0, "y": 0, "curve": "stepped" },
					{ "time": 0.1666, "x": 0, "y": 0 },
					{ "time": 0.4, "x": -414.26, "y": 0, "curve": "stepped" },
					{ "time": 0.5, "x": -414.26, "y": 0 }
				],
				"scale": [
					{ "time": 0, "x": 1, "y": 1 },
					{ "time": 0.1666, "x": 1.615, "y": 1.615 },
					{ "time": 0.4, "x": 1, "y": 1, "curve": "stepped" },
					{ "time": 0.5, "x": 1, "y": 1 }
				]
			},
			"ring": {
				"rotate": [
					{ "time": 0, "angle": 0 },
					{ "time": 0.06, "angle": 90 },
					{ "time": 0.1235, "angle": 180 },
					{ "time": 0.1802, "angle": 270 },
					{ "time": 0.247, "angle": 0 },
					{ "time": 0.3071, "angle": 90 },
					{ "time": 0.3705, "angle": 180 },
					{ "time": 0.4273, "angle": 270 },
					{ "time": 0.5, "angle": 0 }
				],
				"translate": [
					{ "time": 0, "x": 0, "y": 0, "curve": "stepped" },
					{ "time": 0.5, "x": 0, "y": 0 }
				],
				"scale": [
					{ "time": 0, "x": 1, "y": 1, "curve": "stepped" },
					{ "time": 0.5, "x": 1, "y": 1 }
				]
			}
		},
		"draworder": [
			{ "time": 0 },
			{ "time": 0.5 }
		]
	},
	"animation2": {
		"slots": {
			"ball": {
				"attachment": [
					{ "time": 0, "name": "ball" },
					{ "time": 0.4, "name": "ball" },
					{ "time": 0.4666, "name": "ball" },
					{ "time": 0.5, "name": "ball" }
				],
				"color": [
					{ "time": 0, "color": "ffffffff", "curve": "stepped" },
					{ "time": 0.4, "color": "ffffffff", "curve": "stepped" },
					{ "time": 0.5, "color": "ffffffff" }
				]
			},
			"ball2": {
				"attachment": [
					{ "time": 0, "name": "ball" },
					{ "time": 0.4, "name": "ball" },
					{ "time": 0.4666, "name": "ball" },
					{ "time": 0.5, "name": "ball" }
				],
				"color": [
					{ "time": 0, "color": "ffffff00", "curve": "stepped" },
					{ "time": 0.5, "color": "ffffff00" }
				]
			},
			"cloud": {
				"attachment": [
					{ "time": 0, "name": "cloud" },
					{ "time": 0.5, "name": "cloud" }
				],
				"color": [
					{ "time": 0, "color": "ffffff00", "curve": "stepped" },
					{ "time": 0.5, "color": "ffffff00" }
				]
			},
			"cloud2": {
				"attachment": [
					{ "time": 0, "name": "cloud" },
					{ "time": 0.5, "name": "cloud" }
				],
				"color": [
					{ "time": 0, "color": "ffffff00", "curve": "stepped" },
					{ "time": 0.5, "color": "ffffff00" }
				]
			},
			"cloud3": {
				"attachment": [
					{ "time": 0, "name": "cloud" },
					{ "time": 0.5, "name": "cloud" }
				],
				"color": [
					{ "time": 0, "color": "ffffff00", "curve": "stepped" },
					{ "time": 0.5, "color": "ffffff00" }
				]
			},
			"cloud32": {
				"attachment": [
					{ "time": 0, "name": "cloud" },
					{ "time": 0.5, "name": "cloud" }
				],
				"color": [
					{ "time": 0, "color": "ffffff00", "curve": "stepped" },
					{ "time": 0.5, "color": "ffffff00" }
				]
			},
			"cloud322": {
				"attachment": [
					{ "time": 0, "name": "cloud" },
					{ "time": 0.5, "name": "cloud" }
				],
				"color": [
					{ "time": 0, "color": "ffffff00", "curve": "stepped" },
					{ "time": 0.5, "color": "ffffff00" }
				]
			},
			"ring": {
				"attachment": [
					{ "time": 0, "name": "ring" },
					{ "time": 0.5, "name": "ring" }
				],
				"color": [
					{ "time": 0, "color": "ffffff00", "curve": "stepped" },
					{ "time": 0.5, "color": "ffffff00" }
				]
			},
			"star": {
				"attachment": [
					{ "time": 0, "name": "star" },
					{ "time": 0.5, "name": "star" }
				],
				"color": [
					{ "time": 0, "color": "ffffff00", "curve": "stepped" },
					{ "time": 0.5, "color": "ffffff00" }
				]
			},
			"star2": {
				"attachment": [
					{ "time": 0, "name": "star" },
					{ "time": 0.5, "name": "star" }
				],
				"color": [
					{ "time": 0, "color": "ffffff00", "curve": "stepped" },
					{ "time": 0.5, "color": "ffffff00" }
				]
			},
			"star22": {
				"attachment": [
					{ "time": 0, "name": "star" },
					{ "time": 0.5, "name": "star" }
				],
				"color": [
					{ "time": 0, "color": "ffffff00", "curve": "stepped" },
					{ "time": 0.5, "color": "ffffff00" }
				]
			},
			"star222": {
				"attachment": [
					{ "time": 0, "name": "star" },
					{ "time": 0.5, "name": "star" }
				],
				"color": [
					{ "time": 0, "color": "ffffff00", "curve": "stepped" },
					{ "time": 0.5, "color": "ffffff00" }
				]
			}
		},
		"bones": {
			"ball2": {
				"rotate": [
					{ "time": 0, "angle": 0, "curve": "stepped" },
					{ "time": 0.4, "angle": 0, "curve": "stepped" },
					{ "time": 0.5, "angle": 0 }
				],
				"translate": [
					{ "time": 0, "x": 0, "y": 0, "curve": "stepped" },
					{ "time": 0.4, "x": 0, "y": 0, "curve": "stepped" },
					{ "time": 0.5, "x": 0, "y": 0 }
				],
				"scale": [
					{ "time": 0, "x": 1, "y": 1, "curve": "stepped" },
					{ "time": 0.4, "x": 1, "y": 1, "curve": "stepped" },
					{ "time": 0.5, "x": 1, "y": 1 }
				]
			},
			"root": {
				"rotate": [
					{ "time": 0, "angle": 0, "curve": "stepped" },
					{ "time": 0.3333, "angle": 0, "curve": "stepped" },
					{ "time": 0.4, "angle": 0, "curve": "stepped" },
					{ "time": 0.5, "angle": 0 }
				],
				"translate": [
					{ "time": 0, "x": 0, "y": 0, "curve": "stepped" },
					{ "time": 0.3333, "x": 0, "y": 0, "curve": "stepped" },
					{ "time": 0.4, "x": 0, "y": 0, "curve": "stepped" },
					{ "time": 0.5, "x": 0, "y": 0 }
				],
				"scale": [
					{ "time": 0, "x": 1, "y": 1, "curve": "stepped" },
					{ "time": 0.3333, "x": 1, "y": 1, "curve": "stepped" },
					{ "time": 0.3666, "x": 1, "y": 1, "curve": "stepped" },
					{ "time": 0.4, "x": 1, "y": 1, "curve": "stepped" },
					{ "time": 0.5, "x": 1, "y": 1 }
				]
			},
			"ball": {
				"rotate": [
					{ "time": 0, "angle": 0 },
					{ "time": 0.1, "angle": 270 },
					{ "time": 0.2333, "angle": 180 },
					{ "time": 0.3666, "angle": 90 },
					{ "time": 0.5, "angle": 0 }
				],
				"translate": [
					{ "time": 0, "x": 0, "y": 0, "curve": "stepped" },
					{ "time": 0.4, "x": 0, "y": 0, "curve": "stepped" },
					{ "time": 0.5, "x": 0, "y": 0 }
				],
				"scale": [
					{ "time": 0, "x": 1, "y": 1, "curve": "stepped" },
					{ "time": 0.4, "x": 1, "y": 1, "curve": "stepped" },
					{ "time": 0.5, "x": 1, "y": 1 }
				]
			},
			"cloud01": {
				"rotate": [
					{ "time": 0, "angle": 0, "curve": "stepped" },
					{ "time": 0.5, "angle": 0 }
				],
				"translate": [
					{ "time": 0, "x": 0, "y": 0, "curve": "stepped" },
					{ "time": 0.5, "x": 0, "y": 0 }
				],
				"scale": [
					{ "time": 0, "x": 1, "y": 1, "curve": "stepped" },
					{ "time": 0.5, "x": 1, "y": 1 }
				]
			},
			"cloud02": {
				"rotate": [
					{ "time": 0, "angle": 0, "curve": "stepped" },
					{ "time": 0.5, "angle": 0 }
				],
				"translate": [
					{ "time": 0, "x": 0, "y": 0, "curve": "stepped" },
					{ "time": 0.5, "x": 0, "y": 0 }
				],
				"scale": [
					{ "time": 0, "x": 1, "y": 1, "curve": "stepped" },
					{ "time": 0.5, "x": 1, "y": 1 }
				]
			},
			"cloud03": {
				"rotate": [
					{ "time": 0, "angle": 0, "curve": "stepped" },
					{ "time": 0.5, "angle": 0 }
				],
				"translate": [
					{ "time": 0, "x": 0, "y": 0, "curve": "stepped" },
					{ "time": 0.5, "x": 0, "y": 0 }
				],
				"scale": [
					{ "time": 0, "x": 1, "y": 1, "curve": "stepped" },
					{ "time": 0.5, "x": 1, "y": 1 }
				]
			},
			"cloud04": {
				"rotate": [
					{ "time": 0, "angle": 0, "curve": "stepped" },
					{ "time": 0.5, "angle": 0 }
				],
				"translate": [
					{ "time": 0, "x": 0, "y": 0, "curve": "stepped" },
					{ "time": 0.5, "x": 0, "y": 0 }
				],
				"scale": [
					{ "time": 0, "x": 1, "y": 1, "curve": "stepped" },
					{ "time": 0.5, "x": 1, "y": 1 }
				]
			},
			"cloud05": {
				"rotate": [
					{ "time": 0, "angle": 0, "curve": "stepped" },
					{ "time": 0.5, "angle": 0 }
				],
				"translate": [
					{ "time": 0, "x": 0, "y": 0, "curve": "stepped" },
					{ "time": 0.5, "x": 0, "y": 0 }
				],
				"scale": [
					{ "time": 0, "x": 1, "y": 1, "curve": "stepped" },
					{ "time": 0.5, "x": 1, "y": 1 }
				]
			},
			"star01": {
				"rotate": [
					{ "time": 0, "angle": 0, "curve": "stepped" },
					{ "time": 0.5, "angle": 0 }
				],
				"translate": [
					{ "time": 0, "x": 0, "y": 0, "curve": "stepped" },
					{ "time": 0.5, "x": 0, "y": 0 }
				],
				"scale": [
					{ "time": 0, "x": 1, "y": 1, "curve": "stepped" },
					{ "time": 0.5, "x": 1, "y": 1 }
				]
			},
			"star02": {
				"rotate": [
					{ "time": 0, "angle": 0, "curve": "stepped" },
					{ "time": 0.5, "angle": 0 }
				],
				"translate": [
					{ "time": 0, "x": 0, "y": 0, "curve": "stepped" },
					{ "time": 0.5, "x": 0, "y": 0 }
				],
				"scale": [
					{ "time": 0, "x": 1, "y": 1, "curve": "stepped" },
					{ "time": 0.5, "x": 1, "y": 1 }
				]
			},
			"star03": {
				"rotate": [
					{ "time": 0, "angle": 0, "curve": "stepped" },
					{ "time": 0.5, "angle": 0 }
				],
				"translate": [
					{ "time": 0, "x": 0, "y": 0, "curve": "stepped" },
					{ "time": 0.5, "x": 0, "y": 0 }
				],
				"scale": [
					{ "time": 0, "x": 1, "y": 1, "curve": "stepped" },
					{ "time": 0.5, "x": 1, "y": 1 }
				]
			},
			"star04": {
				"rotate": [
					{ "time": 0, "angle": 0, "curve": "stepped" },
					{ "time": 0.5, "angle": 0 }
				],
				"translate": [
					{ "time": 0, "x": 0, "y": 0, "curve": "stepped" },
					{ "time": 0.5, "x": 0, "y": 0 }
				],
				"scale": [
					{ "time": 0, "x": 1, "y": 1, "curve": "stepped" },
					{ "time": 0.5, "x": 1, "y": 1 }
				]
			},
			"ring": {
				"rotate": [
					{ "time": 0, "angle": 0, "curve": "stepped" },
					{ "time": 0.5, "angle": 0 }
				],
				"translate": [
					{ "time": 0, "x": 0, "y": 0, "curve": "stepped" },
					{ "time": 0.5, "x": 0, "y": 0 }
				],
				"scale": [
					{ "time": 0, "x": 1, "y": 1, "curve": "stepped" },
					{ "time": 0.5, "x": 1, "y": 1 }
				]
			}
		},
		"draworder": [
			{ "time": 0 },
			{ "time": 0.5 }
		]
	}
}
}