{"animations":{"attack":{"bones":{"bone":{"rotate":[{"angle":0,"time":0},{"angle":-6.87,"time":0.1666},{"angle":-6.21,"time":0.5},{"angle":0,"curve":"stepped","time":0.6},{"angle":0,"time":0.8666}],"scale":[{"curve":"stepped","time":0,"x":1,"y":1},{"curve":"stepped","time":0.1666,"x":1,"y":1},{"curve":"stepped","time":0.5,"x":1,"y":1},{"curve":"stepped","time":0.6,"x":1,"y":1},{"time":0.8666,"x":1,"y":1}],"translate":[{"curve":"stepped","time":0,"x":0,"y":0},{"curve":"stepped","time":0.1666,"x":0,"y":0},{"time":0.5,"x":0,"y":0},{"time":0.6,"x":-1,"y":0},{"time":0.8666,"x":0,"y":0}]},"bone10":{"rotate":[{"angle":0,"time":0},{"angle":7.6,"time":0.1666},{"angle":8.5,"time":0.5},{"angle":8.17,"time":0.5666},{"angle":-19.41,"time":0.6},{"angle":-16.07,"time":0.7333},{"angle":0,"time":0.8666}],"scale":[{"curve":"stepped","time":0,"x":1,"y":1},{"curve":"stepped","time":0.1666,"x":1,"y":1},{"curve":"stepped","time":0.5,"x":1,"y":1},{"time":0.8666,"x":1,"y":1}],"translate":[{"curve":"stepped","time":0,"x":0,"y":0},{"curve":"stepped","time":0.1666,"x":0,"y":0},{"curve":"stepped","time":0.5,"x":0,"y":0},{"time":0.8666,"x":0,"y":0}]},"bone11":{"rotate":[{"angle":0,"curve":"stepped","time":0},{"angle":0,"curve":"stepped","time":0.1666},{"angle":0,"curve":"stepped","time":0.5},{"angle":0,"time":0.5666},{"angle":15.1,"time":0.6},{"angle":0,"curve":"stepped","time":0.6333},{"angle":0,"time":0.8666}],"scale":[{"curve":"stepped","time":0,"x":1,"y":1},{"curve":"stepped","time":0.1666,"x":1,"y":1},{"curve":"stepped","time":0.5,"x":1,"y":1},{"curve":"stepped","time":0.5666,"x":1,"y":1},{"curve":"stepped","time":0.6,"x":1,"y":1},{"curve":"stepped","time":0.6333,"x":1,"y":1},{"time":0.8666,"x":1,"y":1}],"translate":[{"curve":"stepped","time":0,"x":0,"y":0},{"curve":"stepped","time":0.1666,"x":0,"y":0},{"curve":"stepped","time":0.5,"x":0,"y":0},{"curve":"stepped","time":0.5666,"x":0,"y":0},{"time":0.6,"x":0,"y":0},{"time":0.6333,"x":14.49,"y":-60.26},{"time":0.8,"x":2.89,"y":-2.19},{"time":0.8666,"x":0,"y":0}]},"bone2":{"rotate":[{"angle":0,"time":0},{"angle":-6.87,"time":0.1666},{"angle":-6.21,"time":0.5},{"angle":0,"curve":"stepped","time":0.6},{"angle":0,"time":0.8666}],"scale":[{"curve":"stepped","time":0,"x":1,"y":1},{"curve":"stepped","time":0.1666,"x":1,"y":1},{"curve":"stepped","time":0.5,"x":1,"y":1},{"curve":"stepped","time":0.6,"x":1,"y":1},{"time":0.8666,"x":1,"y":1}],"translate":[{"curve":"stepped","time":0,"x":0,"y":0},{"curve":"stepped","time":0.1666,"x":0,"y":0},{"time":0.5,"x":0,"y":0},{"time":0.6,"x":-1,"y":0},{"time":0.8666,"x":0,"y":0}]},"bone3":{"rotate":[{"angle":0,"time":0},{"angle":6.97,"time":0.1666},{"angle":8.8,"time":0.5},{"angle":-4.74,"time":0.6},{"angle":0,"time":0.8666}],"scale":[{"curve":"stepped","time":0,"x":1,"y":1},{"curve":"stepped","time":0.1666,"x":1,"y":1},{"curve":"stepped","time":0.5,"x":1,"y":1},{"curve":"stepped","time":0.6,"x":1,"y":1},{"time":0.8666,"x":1,"y":1}],"translate":[{"curve":"stepped","time":0,"x":0,"y":0},{"curve":"stepped","time":0.1666,"x":0,"y":0},{"curve":"stepped","time":0.5,"x":0,"y":0},{"curve":"stepped","time":0.6,"x":0,"y":0},{"time":0.8666,"x":0,"y":0}]},"bone4":{"rotate":[{"angle":0,"time":0},{"angle":6.97,"time":0.1666},{"angle":8.8,"time":0.5},{"angle":-4.74,"time":0.6},{"angle":0,"time":0.8666}],"scale":[{"curve":"stepped","time":0,"x":1,"y":1},{"curve":"stepped","time":0.1666,"x":1,"y":1},{"curve":"stepped","time":0.5,"x":1,"y":1},{"curve":"stepped","time":0.6,"x":1,"y":1},{"time":0.8666,"x":1,"y":1}],"translate":[{"curve":"stepped","time":0,"x":0,"y":0},{"curve":"stepped","time":0.1666,"x":0,"y":0},{"curve":"stepped","time":0.5,"x":0,"y":0},{"curve":"stepped","time":0.6,"x":0,"y":0},{"time":0.8666,"x":0,"y":0}]},"bone5":{"rotate":[{"angle":0,"curve":"stepped","time":0},{"angle":0,"curve":"stepped","time":0.1666},{"angle":0,"time":0.5},{"angle":-5.39,"time":0.6},{"angle":0,"time":0.8666}],"scale":[{"curve":"stepped","time":0,"x":1,"y":1},{"curve":"stepped","time":0.1666,"x":1,"y":1},{"curve":"stepped","time":0.5,"x":1,"y":1},{"curve":"stepped","time":0.6,"x":1,"y":1},{"time":0.8666,"x":1,"y":1}],"translate":[{"time":0,"x":0,"y":0},{"curve":"stepped","time":0.1666,"x":-0.11,"y":-1.99},{"time":0.5,"x":-0.11,"y":-1.99},{"curve":"stepped","time":0.6,"x":0,"y":0},{"time":0.8666,"x":0,"y":0}]},"bone6":{"rotate":[{"angle":0,"time":0},{"angle":7.61,"time":0.1666},{"angle":8.06,"time":0.5},{"angle":-4.53,"time":0.6},{"angle":0,"time":0.8666}],"scale":[{"curve":"stepped","time":0,"x":1,"y":1},{"curve":"stepped","time":0.1666,"x":1,"y":1},{"curve":"stepped","time":0.5,"x":1,"y":1},{"curve":"stepped","time":0.6,"x":1,"y":1},{"time":0.8666,"x":1,"y":1}],"translate":[{"time":0,"x":0,"y":0},{"curve":"stepped","time":0.1666,"x":-0.05,"y":-0.99},{"time":0.5,"x":-0.05,"y":-0.99},{"time":0.6,"x":1,"y":1},{"time":0.8666,"x":0,"y":0}]},"bone7":{"rotate":[{"angle":0,"time":0},{"angle":7.61,"time":0.1666},{"angle":8.06,"time":0.5},{"angle":-4.53,"time":0.6},{"angle":0,"time":0.8666}],"scale":[{"curve":"stepped","time":0,"x":1,"y":1},{"curve":"stepped","time":0.1666,"x":1,"y":1},{"curve":"stepped","time":0.5,"x":1,"y":1},{"curve":"stepped","time":0.6,"x":1,"y":1},{"time":0.8666,"x":1,"y":1}],"translate":[{"time":0,"x":0,"y":0},{"curve":"stepped","time":0.1666,"x":-0.05,"y":-0.99},{"time":0.5,"x":-0.05,"y":-0.99},{"time":0.6,"x":1,"y":1},{"time":0.8666,"x":0,"y":0}]},"bone8":{"rotate":[{"angle":0,"time":0},{"angle":7.6,"time":0.1666},{"angle":8.5,"time":0.5},{"angle":-36.76,"time":0.5666},{"angle":-31.1,"time":0.6},{"angle":-4.51,"time":0.7333},{"angle":0,"time":0.8666}],"scale":[{"curve":"stepped","time":0,"x":1,"y":1},{"curve":"stepped","time":0.1666,"x":1,"y":1},{"curve":"stepped","time":0.5,"x":1,"y":1},{"time":0.8666,"x":1,"y":1}],"translate":[{"curve":"stepped","time":0,"x":0,"y":0},{"curve":"stepped","time":0.1666,"x":0,"y":0},{"curve":"stepped","time":0.5,"x":0,"y":0},{"time":0.8666,"x":0,"y":0}]},"bone9":{"rotate":[{"angle":0,"time":0},{"angle":7.6,"time":0.1666},{"angle":8.5,"time":0.5},{"angle":8.17,"time":0.5666},{"angle":-19.41,"time":0.6},{"angle":-16.07,"time":0.7333},{"angle":0,"time":0.8666}],"scale":[{"curve":"stepped","time":0,"x":1,"y":1},{"curve":"stepped","time":0.1666,"x":1,"y":1},{"curve":"stepped","time":0.5,"x":1,"y":1},{"time":0.8666,"x":1,"y":1}],"translate":[{"curve":"stepped","time":0,"x":0,"y":0},{"curve":"stepped","time":0.1666,"x":0,"y":0},{"curve":"stepped","time":0.5,"x":0,"y":0},{"time":0.8666,"x":0,"y":0}]},"cheshen":{"rotate":[{"angle":0,"time":0},{"angle":3.15,"time":0.1666},{"angle":3.6,"time":0.5},{"angle":-0.8,"time":0.6},{"angle":0,"time":0.8666}],"scale":[{"curve":"stepped","time":0,"x":1,"y":1},{"curve":"stepped","time":0.1666,"x":1,"y":1},{"curve":"stepped","time":0.5,"x":1,"y":1},{"curve":"stepped","time":0.6,"x":1,"y":1},{"time":0.8666,"x":1,"y":1}],"translate":[{"time":0,"x":0,"y":0},{"time":0.1666,"x":-2,"y":0},{"time":0.5,"x":-3,"y":0},{"time":0.6,"x":2,"y":0},{"time":0.8666,"x":0,"y":0}]},"dizuo":{"rotate":[{"angle":0,"curve":"stepped","time":0},{"angle":0,"curve":"stepped","time":0.1666},{"angle":0,"curve":"stepped","time":0.5},{"angle":0,"curve":"stepped","time":0.6},{"angle":0,"time":0.8666}],"scale":[{"curve":"stepped","time":0,"x":1,"y":1},{"curve":"stepped","time":0.1666,"x":1,"y":1},{"curve":"stepped","time":0.5,"x":1,"y":1},{"curve":"stepped","time":0.6,"x":1,"y":1},{"time":0.8666,"x":1,"y":1}],"translate":[{"curve":"stepped","time":0,"x":0,"y":0},{"curve":"stepped","time":0.1666,"x":0,"y":0},{"time":0.5,"x":0,"y":0},{"time":0.6,"x":-1,"y":0},{"time":0.8666,"x":0,"y":0}]},"root":{"rotate":[{"angle":0,"curve":"stepped","time":0},{"angle":0,"curve":"stepped","time":0.1666},{"angle":0,"curve":"stepped","time":0.5},{"angle":0,"curve":"stepped","time":0.6},{"angle":0,"time":0.8666}],"scale":[{"time":0,"x":1,"y":1},{"curve":"stepped","time":0.1666,"x":1,"y":0.976},{"time":0.5,"x":1,"y":0.976},{"curve":"stepped","time":0.6,"x":1,"y":1},{"time":0.8666,"x":1,"y":1}],"translate":[{"time":0,"x":0,"y":0},{"curve":"stepped","time":0.1666,"x":2,"y":0},{"time":0.5,"x":2,"y":0},{"curve":"stepped","time":0.6,"x":0,"y":0},{"time":0.8666,"x":0,"y":0}]},"shadow":{"rotate":[{"angle":0,"curve":"stepped","time":0},{"angle":0,"curve":"stepped","time":0.1666},{"angle":0,"curve":"stepped","time":0.5},{"angle":0,"curve":"stepped","time":0.6},{"angle":0,"time":0.8666}],"scale":[{"time":0,"x":1,"y":1},{"time":0.1666,"x":1.06,"y":1.06},{"time":0.5,"x":1.047,"y":1.047},{"time":0.6,"x":0.919,"y":0.919},{"time":0.8666,"x":1,"y":1}],"translate":[{"curve":"stepped","time":0,"x":0,"y":0},{"curve":"stepped","time":0.1666,"x":0,"y":0},{"curve":"stepped","time":0.5,"x":0,"y":0},{"curve":"stepped","time":0.6,"x":0,"y":0},{"time":0.8666,"x":0,"y":0}]}},"slots":{"_0007_shitou":{"attachment":[{"name":"_0007_shitou","time":0},{"name":"shitouying","time":0.6},{"name":null,"time":0.6333},{"name":"_0007_shitou","time":0.8}],"color":[{"color":"ffffffff","curve":"stepped","time":0},{"color":"ffffffff","curve":"stepped","time":0.5666},{"color":"ffffffff","curve":"stepped","time":0.6},{"color":"ffffffff","time":0.6333},{"color":"ffffff00","time":0.8},{"color":"ffffffff","time":0.8666}]}}},"celebrate":{"bones":{"bone":{"rotate":[{"angle":0,"time":0},{"angle":14.4,"curve":"stepped","time":0.3333},{"angle":14.4,"time":0.6666},{"angle":0,"curve":"stepped","time":1},{"angle":0,"time":1.3333}],"scale":[{"curve":"stepped","time":0,"x":1,"y":1},{"curve":"stepped","time":1,"x":1,"y":1},{"time":1.3333,"x":1,"y":1}],"translate":[{"time":0,"x":0,"y":0},{"curve":"stepped","time":0.3333,"x":-1.25,"y":-1.78},{"time":0.6666,"x":-1.25,"y":-1.78},{"curve":"stepped","time":1,"x":0,"y":0},{"time":1.3333,"x":0,"y":0}]},"bone10":{"rotate":[{"angle":0,"time":0},{"angle":3.56,"time":0.3333},{"angle":0.72,"time":1},{"angle":0,"time":1.3333}],"scale":[{"curve":"stepped","time":0,"x":1,"y":1},{"time":1.3333,"x":1,"y":1}],"translate":[{"curve":"stepped","time":0,"x":0,"y":0},{"time":1.3333,"x":0,"y":0}]},"bone11":{"rotate":[{"angle":0,"curve":"stepped","time":0},{"angle":0,"time":1.3333}],"scale":[{"curve":"stepped","time":0,"x":1,"y":1},{"time":1.3333,"x":1,"y":1}],"translate":[{"curve":"stepped","time":0,"x":0,"y":0},{"time":1.3333,"x":0,"y":0}]},"bone2":{"rotate":[{"angle":0,"time":0},{"angle":14.4,"curve":"stepped","time":0.3333},{"angle":14.4,"time":0.6666},{"angle":0,"curve":"stepped","time":1},{"angle":0,"time":1.3333}],"scale":[{"curve":"stepped","time":0,"x":1,"y":1},{"curve":"stepped","time":1,"x":1,"y":1},{"time":1.3333,"x":1,"y":1}],"translate":[{"time":0,"x":0,"y":0},{"curve":"stepped","time":0.3333,"x":-1.25,"y":-1.78},{"time":0.6666,"x":-1.25,"y":-1.78},{"curve":"stepped","time":1,"x":0,"y":0},{"time":1.3333,"x":0,"y":0}]},"bone3":{"rotate":[{"angle":0,"time":0},{"angle":-2.66,"curve":"stepped","time":0.3333},{"angle":-2.66,"time":0.6666},{"angle":0,"curve":"stepped","time":1},{"angle":0,"time":1.3333}],"scale":[{"curve":"stepped","time":0,"x":1,"y":1},{"curve":"stepped","time":1,"x":1,"y":1},{"time":1.3333,"x":1,"y":1}],"translate":[{"curve":"stepped","time":0,"x":0,"y":0},{"curve":"stepped","time":1,"x":0,"y":0},{"time":1.3333,"x":0,"y":0}]},"bone4":{"rotate":[{"angle":0,"time":0},{"angle":-2.66,"curve":"stepped","time":0.3333},{"angle":-2.66,"time":0.6666},{"angle":0,"curve":"stepped","time":1},{"angle":0,"time":1.3333}],"scale":[{"curve":"stepped","time":0,"x":1,"y":1},{"curve":"stepped","time":1,"x":1,"y":1},{"time":1.3333,"x":1,"y":1}],"translate":[{"curve":"stepped","time":0,"x":0,"y":0},{"curve":"stepped","time":1,"x":0,"y":0},{"time":1.3333,"x":0,"y":0}]},"bone5":{"rotate":[{"angle":0,"curve":"stepped","time":0},{"angle":0,"time":1.3333}],"scale":[{"curve":"stepped","time":0,"x":1,"y":1},{"time":1.3333,"x":1,"y":1}],"translate":[{"curve":"stepped","time":0,"x":0,"y":0},{"time":1.3333,"x":0,"y":0}]},"bone6":{"rotate":[{"angle":0,"time":0},{"angle":-2.7,"time":0.3333},{"angle":0,"time":1.3333}],"scale":[{"curve":"stepped","time":0,"x":1,"y":1},{"time":1.3333,"x":1,"y":1}],"translate":[{"time":0,"x":0,"y":0},{"time":0.3333,"x":2.36,"y":3.88},{"time":0.6666,"x":0,"y":-0.53},{"time":1.3333,"x":0,"y":0}]},"bone7":{"rotate":[{"angle":0,"time":0},{"angle":-2.7,"time":0.3333},{"angle":0,"time":1.3333}],"scale":[{"curve":"stepped","time":0,"x":1,"y":1},{"time":1.3333,"x":1,"y":1}],"translate":[{"time":0,"x":0,"y":0},{"time":0.3333,"x":1.76,"y":1.86},{"time":0.6666,"x":0,"y":-1},{"time":1.3333,"x":0,"y":0}]},"bone8":{"rotate":[{"angle":0,"time":0},{"angle":-14.91,"time":0.3333},{"angle":0.72,"time":1},{"angle":0,"time":1.3333}],"scale":[{"curve":"stepped","time":0,"x":1,"y":1},{"time":1.3333,"x":1,"y":1}],"translate":[{"curve":"stepped","time":0,"x":0,"y":0},{"time":1.3333,"x":0,"y":0}]},"bone9":{"rotate":[{"angle":0,"time":0},{"angle":3.56,"time":0.3333},{"angle":0.72,"time":1},{"angle":0,"time":1.3333}],"scale":[{"curve":"stepped","time":0,"x":1,"y":1},{"time":1.3333,"x":1,"y":1}],"translate":[{"curve":"stepped","time":0,"x":0,"y":0},{"time":1.3333,"x":0,"y":0}]},"cheshen":{"rotate":[{"angle":0,"time":0},{"angle":0.44,"time":0.6666},{"angle":0,"time":1.3333}],"scale":[{"curve":"stepped","time":0,"x":1,"y":1},{"time":1.3333,"x":1,"y":1}],"translate":[{"curve":"stepped","time":0,"x":0,"y":0},{"time":1.3333,"x":0,"y":0}]},"dizuo":{"rotate":[{"angle":0,"curve":"stepped","time":0},{"angle":0,"time":1.3333}],"scale":[{"curve":"stepped","time":0,"x":1,"y":1},{"time":1.3333,"x":1,"y":1}],"translate":[{"curve":"stepped","time":0,"x":0,"y":0},{"time":1.3333,"x":0,"y":0}]},"root":{"rotate":[{"angle":0,"curve":"stepped","time":0},{"angle":0,"curve":"stepped","time":1},{"angle":0,"time":1.3333}],"scale":[{"time":0,"x":1,"y":1},{"time":0.6666,"x":1,"y":0.972},{"curve":"stepped","time":1,"x":1,"y":1},{"time":1.3333,"x":1,"y":1}],"translate":[{"time":0,"x":0,"y":0},{"curve":"stepped","time":0.3333,"x":-11.7,"y":0},{"time":0.6666,"x":-11.7,"y":0},{"curve":"stepped","time":1,"x":0,"y":0},{"time":1.3333,"x":0,"y":0}]},"shadow":{"rotate":[{"angle":0,"curve":"stepped","time":0},{"angle":0,"curve":"stepped","time":1},{"angle":0,"time":1.3333}],"scale":[{"time":0,"x":1,"y":1},{"time":0.6666,"x":0.96,"y":0.96},{"curve":"stepped","time":1,"x":1,"y":1},{"time":1.3333,"x":1,"y":1}],"translate":[{"curve":"stepped","time":0,"x":0,"y":0},{"curve":"stepped","time":0.3333,"x":0,"y":0},{"curve":"stepped","time":0.6666,"x":0,"y":0},{"curve":"stepped","time":1,"x":0,"y":0},{"time":1.3333,"x":0,"y":0}]}},"slots":{"_0007_shitou":{"attachment":[{"name":"_0007_shitou","time":0},{"name":"_0007_shitou","time":1.3333}],"color":[{"color":"ffffffff","curve":"stepped","time":0},{"color":"ffffffff","time":1.3333}]}}},"death":{"bones":{"bone":{"rotate":[{"angle":0,"curve":"stepped","time":0},{"angle":0,"time":0.1666},{"angle":-51.93,"time":0.3333}],"scale":[{"curve":"stepped","time":0,"x":1,"y":1},{"time":0.3333,"x":1,"y":1}],"translate":[{"curve":"stepped","time":0,"x":0,"y":0},{"time":0.1666,"x":0,"y":0},{"time":0.3333,"x":-12.95,"y":-6.48}]},"bone10":{"rotate":[{"angle":0,"time":0},{"angle":2.22,"time":0.1666},{"angle":-28.22,"time":0.3333}],"scale":[{"curve":"stepped","time":0,"x":1,"y":1},{"time":0.3333,"x":1,"y":1}],"translate":[{"curve":"stepped","time":0,"x":0,"y":0},{"time":0.1666,"x":0,"y":0},{"time":0.3333,"x":26.91,"y":46.17}]},"bone11":{"rotate":[{"angle":0,"curve":"stepped","time":0},{"angle":0,"time":0.1666},{"angle":-30,"time":0.3333}],"scale":[{"curve":"stepped","time":0,"x":1,"y":1},{"time":0.3333,"x":1,"y":1}],"translate":[{"time":0,"x":0,"y":0},{"time":0.1666,"x":-6.73,"y":-14.59},{"time":0.3333,"x":0.95,"y":0.73}]},"bone2":{"rotate":[{"angle":0,"curve":"stepped","time":0},{"angle":0,"time":0.1666},{"angle":-45.24,"time":0.3333}],"scale":[{"curve":"stepped","time":0,"x":1,"y":1},{"time":0.3333,"x":1,"y":1}],"translate":[{"curve":"stepped","time":0,"x":0,"y":0},{"time":0.1666,"x":0,"y":0},{"time":0.3333,"x":1.07,"y":-14.03}]},"bone3":{"rotate":[{"angle":0,"time":0},{"angle":9.95,"time":0.1666},{"angle":72.69,"time":0.3333}],"scale":[{"curve":"stepped","time":0,"x":1,"y":1},{"time":0.3333,"x":1,"y":1}],"translate":[{"curve":"stepped","time":0,"x":0,"y":0},{"time":0.1666,"x":0,"y":0},{"time":0.3333,"x":6.48,"y":19.44}]},"bone4":{"rotate":[{"angle":0,"time":0},{"angle":9.95,"time":0.1666},{"angle":-10.41,"time":0.3333}],"scale":[{"curve":"stepped","time":0,"x":1,"y":1},{"time":0.3333,"x":1,"y":1}],"translate":[{"curve":"stepped","time":0,"x":0,"y":0},{"time":0.1666,"x":0,"y":0},{"time":0.3333,"x":9.18,"y":-18.89}]},"bone5":{"rotate":[{"angle":0,"time":0},{"angle":-17.89,"time":0.1666},{"angle":8.1,"time":0.3333}],"scale":[{"curve":"stepped","time":0,"x":1,"y":1},{"time":0.3333,"x":1,"y":1}],"translate":[{"time":0,"x":0,"y":0},{"time":0.1666,"x":-1.44,"y":-4.22},{"time":0.3333,"x":15.66,"y":-25.37}]},"bone6":{"rotate":[{"angle":0,"curve":"stepped","time":0},{"angle":0,"time":0.1666},{"angle":-3.87,"time":0.3333}],"scale":[{"curve":"stepped","time":0,"x":1,"y":1},{"time":0.3333,"x":1,"y":1}],"translate":[{"time":0,"x":0,"y":0},{"time":0.1666,"x":2,"y":0},{"time":0.3333,"x":1.62,"y":-9.17}]},"bone7":{"rotate":[{"angle":0,"curve":"stepped","time":0},{"angle":0,"time":0.1666},{"angle":24.54,"time":0.3333}],"scale":[{"curve":"stepped","time":0,"x":1,"y":1},{"time":0.3333,"x":1,"y":1}],"translate":[{"time":0,"x":0,"y":0},{"time":0.1666,"x":2,"y":0},{"time":0.3333,"x":-6.47,"y":-10.25}]},"bone8":{"rotate":[{"angle":0,"time":0},{"angle":2.22,"time":0.1666},{"angle":27.25,"time":0.3333}],"scale":[{"curve":"stepped","time":0,"x":1,"y":1},{"time":0.3333,"x":1,"y":1}],"translate":[{"curve":"stepped","time":0,"x":0,"y":0},{"curve":"stepped","time":0.1666,"x":0,"y":0},{"time":0.3333,"x":0,"y":0}]},"bone9":{"rotate":[{"angle":0,"time":0},{"angle":2.22,"time":0.1666},{"angle":0,"time":0.3333}],"scale":[{"curve":"stepped","time":0,"x":1,"y":1},{"time":0.3333,"x":1,"y":1}],"translate":[{"curve":"stepped","time":0,"x":0,"y":0},{"curve":"stepped","time":0.1666,"x":0,"y":0},{"time":0.3333,"x":0,"y":0}]},"cheshen":{"rotate":[{"angle":0,"time":0},{"angle":4.43,"time":0.1666},{"angle":0,"time":0.3333}],"scale":[{"curve":"stepped","time":0,"x":1,"y":1},{"time":0.3333,"x":1,"y":1}],"translate":[{"time":0,"x":0,"y":0},{"time":0.1666,"x":-3,"y":-2.69},{"time":0.3333,"x":0,"y":-10.8}]},"dizuo":{"rotate":[{"angle":0,"curve":"stepped","time":0},{"angle":0,"curve":"stepped","time":0.1666},{"angle":0,"time":0.3333}],"scale":[{"curve":"stepped","time":0,"x":1,"y":1},{"time":0.3333,"x":1,"y":1}],"translate":[{"curve":"stepped","time":0,"x":0,"y":0},{"time":0.1666,"x":0,"y":0},{"time":0.3333,"x":0,"y":-8.09}]},"root":{"rotate":[{"angle":0,"curve":"stepped","time":0},{"angle":0,"curve":"stepped","time":0.1666},{"angle":0,"time":0.3333}],"scale":[{"time":0,"x":1,"y":1},{"time":0.1666,"x":1.057,"y":1.087},{"time":0.3333,"x":1,"y":1}],"translate":[{"time":0,"x":0,"y":0},{"time":0.1666,"x":-5,"y":0},{"time":0.3333,"x":0,"y":0}]},"shadow":{"rotate":[{"angle":0,"curve":"stepped","time":0},{"angle":0,"curve":"stepped","time":0.1666},{"angle":0,"time":0.3333}],"scale":[{"time":0,"x":1,"y":1},{"time":0.1666,"x":1.087,"y":1.087},{"time":0.3333,"x":1.332,"y":1.257}],"translate":[{"curve":"stepped","time":0,"x":0,"y":0},{"time":0.1666,"x":0,"y":0},{"time":0.3333,"x":-4.68,"y":0}]}},"slots":{"_0007_shitou":{"attachment":[{"name":"_0007_shitou","time":0},{"name":"_0007_shitou","time":0.3333}],"color":[{"color":"ffffffff","curve":"stepped","time":0},{"color":"ffffffff","time":0.3333}]}}},"dizzy":{"bones":{"bone":{"rotate":[{"angle":0,"curve":"stepped","time":0},{"angle":0,"time":1.3333}],"scale":[{"curve":"stepped","time":0,"x":1,"y":1},{"time":1.3333,"x":1,"y":1}],"translate":[{"time":0,"x":0,"y":0},{"time":0.6666,"x":1,"y":0},{"time":1.3333,"x":0,"y":0}]},"bone10":{"rotate":[{"angle":0,"time":0},{"angle":-1.43,"time":0.3333},{"angle":0.72,"time":1},{"angle":0,"time":1.3333}],"scale":[{"curve":"stepped","time":0,"x":1,"y":1},{"time":1.3333,"x":1,"y":1}],"translate":[{"curve":"stepped","time":0,"x":0,"y":0},{"time":1.3333,"x":0,"y":0}]},"bone11":{"rotate":[{"angle":0,"curve":"stepped","time":0},{"angle":0,"time":1.3333}],"scale":[{"curve":"stepped","time":0,"x":1,"y":1},{"time":1.3333,"x":1,"y":1}],"translate":[{"curve":"stepped","time":0,"x":0,"y":0},{"time":1.3333,"x":0,"y":0}]},"bone2":{"rotate":[{"angle":0,"curve":"stepped","time":0},{"angle":0,"time":1.3333}],"scale":[{"curve":"stepped","time":0,"x":1,"y":1},{"time":1.3333,"x":1,"y":1}],"translate":[{"time":0,"x":0,"y":0},{"time":0.6666,"x":1,"y":0},{"time":1.3333,"x":0,"y":0}]},"bone3":{"rotate":[{"angle":0,"curve":"stepped","time":0},{"angle":0,"time":1.3333}],"scale":[{"curve":"stepped","time":0,"x":1,"y":1},{"time":1.3333,"x":1,"y":1}],"translate":[{"curve":"stepped","time":0,"x":0,"y":0},{"time":1.3333,"x":0,"y":0}]},"bone4":{"rotate":[{"angle":0,"curve":"stepped","time":0},{"angle":0,"time":1.3333}],"scale":[{"curve":"stepped","time":0,"x":1,"y":1},{"time":1.3333,"x":1,"y":1}],"translate":[{"curve":"stepped","time":0,"x":0,"y":0},{"time":1.3333,"x":0,"y":0}]},"bone5":{"rotate":[{"angle":0,"curve":"stepped","time":0},{"angle":0,"time":1.3333}],"scale":[{"curve":"stepped","time":0,"x":1,"y":1},{"time":1.3333,"x":1,"y":1}],"translate":[{"curve":"stepped","time":0,"x":0,"y":0},{"time":1.3333,"x":0,"y":0}]},"bone6":{"rotate":[{"angle":0,"curve":"stepped","time":0},{"angle":0,"time":1.3333}],"scale":[{"curve":"stepped","time":0,"x":1,"y":1},{"time":1.3333,"x":1,"y":1}],"translate":[{"time":0,"x":0,"y":0},{"time":0.6666,"x":0,"y":-0.53},{"time":1.3333,"x":0,"y":0}]},"bone7":{"rotate":[{"angle":0,"curve":"stepped","time":0},{"angle":0,"time":1.3333}],"scale":[{"curve":"stepped","time":0,"x":1,"y":1},{"time":1.3333,"x":1,"y":1}],"translate":[{"time":0,"x":0,"y":0},{"time":0.6666,"x":0,"y":-1},{"time":1.3333,"x":0,"y":0}]},"bone8":{"rotate":[{"angle":0,"time":0},{"angle":-1.43,"time":0.3333},{"angle":0.72,"time":1},{"angle":0,"time":1.3333}],"scale":[{"curve":"stepped","time":0,"x":1,"y":1},{"time":1.3333,"x":1,"y":1}],"translate":[{"curve":"stepped","time":0,"x":0,"y":0},{"time":1.3333,"x":0,"y":0}]},"bone9":{"rotate":[{"angle":0,"time":0},{"angle":-1.43,"time":0.3333},{"angle":0.72,"time":1},{"angle":0,"time":1.3333}],"scale":[{"curve":"stepped","time":0,"x":1,"y":1},{"time":1.3333,"x":1,"y":1}],"translate":[{"curve":"stepped","time":0,"x":0,"y":0},{"time":1.3333,"x":0,"y":0}]},"cheshen":{"rotate":[{"angle":0,"time":0},{"angle":0.44,"time":0.6666},{"angle":0,"time":1.3333}],"scale":[{"curve":"stepped","time":0,"x":1,"y":1},{"time":1.3333,"x":1,"y":1}],"translate":[{"curve":"stepped","time":0,"x":0,"y":0},{"time":1.3333,"x":0,"y":0}]},"dizuo":{"rotate":[{"angle":0,"curve":"stepped","time":0},{"angle":0,"time":1.3333}],"scale":[{"curve":"stepped","time":0,"x":1,"y":1},{"time":1.3333,"x":1,"y":1}],"translate":[{"curve":"stepped","time":0,"x":0,"y":0},{"time":1.3333,"x":0,"y":0}]},"root":{"rotate":[{"angle":0,"curve":"stepped","time":0},{"angle":0,"time":1.3333}],"scale":[{"time":0,"x":1,"y":1},{"time":0.6666,"x":1,"y":0.972},{"time":1.3333,"x":1,"y":1}],"translate":[{"time":0,"x":0,"y":0},{"time":0.6666,"x":-2.31,"y":0},{"time":1.3333,"x":0,"y":0}]},"shadow":{"rotate":[{"angle":0,"curve":"stepped","time":0},{"angle":0,"time":1.3333}],"scale":[{"time":0,"x":1,"y":1},{"time":0.6666,"x":1.085,"y":1.085},{"time":1.3333,"x":1,"y":1}],"translate":[{"curve":"stepped","time":0,"x":0,"y":0},{"curve":"stepped","time":0.6666,"x":0,"y":0},{"time":1.3333,"x":0,"y":0}]}},"slots":{"_0007_shitou":{"attachment":[{"name":"_0007_shitou","time":0},{"name":"_0007_shitou","time":1.3333}],"color":[{"color":"ffffffff","curve":"stepped","time":0},{"color":"ffffffff","time":1.3333}]}}},"dodge":{"bones":{"bone":{"rotate":[{"angle":0,"time":0},{"angle":19.21,"time":0.1},{"angle":-18.71,"time":0.3333},{"angle":0,"time":0.5}],"scale":[{"curve":"stepped","time":0,"x":1,"y":1},{"time":0.5,"x":1,"y":1}],"translate":[{"time":0,"x":0,"y":0},{"time":0.1,"x":-31.29,"y":15.63},{"time":0.3333,"x":-43.92,"y":24.5},{"time":0.5,"x":0,"y":0}]},"bone10":{"rotate":[{"angle":0,"time":0},{"angle":-1.43,"time":0.1},{"angle":0.72,"time":0.3333},{"angle":0,"time":0.5}],"scale":[{"curve":"stepped","time":0,"x":1,"y":1},{"time":0.5,"x":1,"y":1}],"translate":[{"curve":"stepped","time":0,"x":0,"y":0},{"time":0.5,"x":0,"y":0}]},"bone11":{"rotate":[{"angle":0,"curve":"stepped","time":0},{"angle":0,"time":0.5}],"scale":[{"curve":"stepped","time":0,"x":1,"y":1},{"time":0.5,"x":1,"y":1}],"translate":[{"curve":"stepped","time":0,"x":0,"y":0},{"time":0.5,"x":0,"y":0}]},"bone2":{"rotate":[{"angle":0,"time":0},{"angle":19.21,"time":0.1},{"angle":-18.71,"time":0.3333},{"angle":0,"time":0.5}],"scale":[{"curve":"stepped","time":0,"x":1,"y":1},{"time":0.5,"x":1,"y":1}],"translate":[{"time":0,"x":0,"y":0},{"time":0.1,"x":-31.29,"y":15.63},{"time":0.3333,"x":-43.92,"y":24.5},{"time":0.5,"x":0,"y":0}]},"bone3":{"rotate":[{"angle":0,"curve":"stepped","time":0},{"angle":0,"time":0.5}],"scale":[{"curve":"stepped","time":0,"x":1,"y":1},{"time":0.5,"x":1,"y":1}],"translate":[{"curve":"stepped","time":0,"x":0,"y":0},{"time":0.5,"x":0,"y":0}]},"bone4":{"rotate":[{"angle":0,"curve":"stepped","time":0},{"angle":0,"time":0.5}],"scale":[{"curve":"stepped","time":0,"x":1,"y":1},{"time":0.5,"x":1,"y":1}],"translate":[{"curve":"stepped","time":0,"x":0,"y":0},{"time":0.5,"x":0,"y":0}]},"bone5":{"rotate":[{"angle":0,"curve":"stepped","time":0},{"angle":0,"time":0.5}],"scale":[{"curve":"stepped","time":0,"x":1,"y":1},{"time":0.5,"x":1,"y":1}],"translate":[{"curve":"stepped","time":0,"x":0,"y":0},{"time":0.5,"x":0,"y":0}]},"bone6":{"rotate":[{"angle":0,"curve":"stepped","time":0},{"angle":0,"time":0.5}],"scale":[{"curve":"stepped","time":0,"x":1,"y":1},{"time":0.5,"x":1,"y":1}],"translate":[{"time":0,"x":0,"y":0},{"time":0.3333,"x":0,"y":-0.53},{"time":0.5,"x":0,"y":0}]},"bone7":{"rotate":[{"angle":0,"curve":"stepped","time":0},{"angle":0,"time":0.5}],"scale":[{"curve":"stepped","time":0,"x":1,"y":1},{"time":0.5,"x":1,"y":1}],"translate":[{"time":0,"x":0,"y":0},{"time":0.3333,"x":0,"y":-1},{"time":0.5,"x":0,"y":0}]},"bone8":{"rotate":[{"angle":0,"time":0},{"angle":-1.43,"time":0.1},{"angle":0.72,"time":0.3333},{"angle":0,"time":0.5}],"scale":[{"curve":"stepped","time":0,"x":1,"y":1},{"time":0.5,"x":1,"y":1}],"translate":[{"curve":"stepped","time":0,"x":0,"y":0},{"time":0.5,"x":0,"y":0}]},"bone9":{"rotate":[{"angle":0,"time":0},{"angle":-1.43,"time":0.1},{"angle":0.72,"time":0.3333},{"angle":0,"time":0.5}],"scale":[{"curve":"stepped","time":0,"x":1,"y":1},{"time":0.5,"x":1,"y":1}],"translate":[{"curve":"stepped","time":0,"x":0,"y":0},{"time":0.5,"x":0,"y":0}]},"cheshen":{"rotate":[{"angle":0,"time":0},{"angle":0.44,"time":0.3333},{"angle":0,"time":0.5}],"scale":[{"curve":"stepped","time":0,"x":1,"y":1},{"time":0.5,"x":1,"y":1}],"translate":[{"time":0,"x":0,"y":0},{"time":0.1,"x":-31.59,"y":15.63},{"time":0.3333,"x":-44.22,"y":24.5},{"time":0.5,"x":0,"y":0}]},"dizuo":{"rotate":[{"angle":0,"curve":"stepped","time":0},{"angle":0,"time":0.5}],"scale":[{"curve":"stepped","time":0,"x":1,"y":1},{"time":0.5,"x":1,"y":1}],"translate":[{"time":0,"x":0,"y":0},{"time":0.1,"x":-31.59,"y":15.63},{"time":0.3333,"x":-44.22,"y":24.5},{"time":0.5,"x":0,"y":0}]},"root":{"rotate":[{"angle":0,"curve":"stepped","time":0},{"angle":0,"time":0.5}],"scale":[{"time":0,"x":1,"y":1},{"time":0.3333,"x":1,"y":0.972},{"time":0.5,"x":1,"y":1}],"translate":[{"time":0,"x":0,"y":0},{"time":0.3333,"x":-2.31,"y":0},{"time":0.5,"x":0,"y":0}]},"shadow":{"rotate":[{"angle":0,"curve":"stepped","time":0},{"angle":0,"time":0.5}],"scale":[{"time":0,"x":1,"y":1},{"time":0.3333,"x":1.085,"y":1.085},{"time":0.5,"x":1,"y":1}],"translate":[{"time":0,"x":0,"y":0},{"time":0.1,"x":-31.59,"y":15.63},{"time":0.3333,"x":-44.22,"y":24.5},{"time":0.5,"x":0,"y":0}]}},"slots":{"_0007_shitou":{"attachment":[{"name":"_0007_shitou","time":0},{"name":"_0007_shitou","time":0.5}],"color":[{"color":"ffffffff","curve":"stepped","time":0},{"color":"ffffffff","time":0.5}]}}},"injured":{"bones":{"bone":{"rotate":[{"angle":0,"curve":"stepped","time":0},{"angle":0,"time":0.1},{"angle":14.4,"time":0.2333},{"angle":0,"time":0.5}],"scale":[{"curve":"stepped","time":0,"x":1,"y":1},{"curve":"stepped","time":0.1,"x":1,"y":1},{"time":0.5,"x":1,"y":1}],"translate":[{"curve":"stepped","time":0,"x":0,"y":0},{"time":0.1,"x":0,"y":0},{"time":0.2333,"x":-1.25,"y":-1.78},{"time":0.5,"x":0,"y":0}]},"bone10":{"rotate":[{"angle":0,"time":0},{"angle":2.73,"time":0.1},{"angle":-2.72,"time":0.2333},{"angle":-7.46,"time":0.3666},{"angle":0,"time":0.5}],"scale":[{"curve":"stepped","time":0,"x":1,"y":1},{"curve":"stepped","time":0.1,"x":1,"y":1},{"time":0.5,"x":1,"y":1}],"translate":[{"curve":"stepped","time":0,"x":0,"y":0},{"curve":"stepped","time":0.1,"x":0,"y":0},{"curve":"stepped","time":0.2333,"x":0,"y":0},{"time":0.5,"x":0,"y":0}]},"bone11":{"rotate":[{"angle":0,"curve":"stepped","time":0},{"angle":0,"curve":"stepped","time":0.1},{"angle":0,"curve":"stepped","time":0.2333},{"angle":0,"time":0.5}],"scale":[{"curve":"stepped","time":0,"x":1,"y":1},{"curve":"stepped","time":0.1,"x":1,"y":1},{"time":0.5,"x":1,"y":1}],"translate":[{"curve":"stepped","time":0,"x":0,"y":0},{"curve":"stepped","time":0.1,"x":0,"y":0},{"time":0.2333,"x":0,"y":0},{"time":0.3666,"x":-0.74,"y":-2.96},{"time":0.5,"x":0,"y":0}]},"bone2":{"rotate":[{"angle":0,"curve":"stepped","time":0},{"angle":0,"time":0.1},{"angle":14.4,"time":0.2333},{"angle":0,"time":0.5}],"scale":[{"curve":"stepped","time":0,"x":1,"y":1},{"curve":"stepped","time":0.1,"x":1,"y":1},{"time":0.5,"x":1,"y":1}],"translate":[{"curve":"stepped","time":0,"x":0,"y":0},{"time":0.1,"x":0,"y":0},{"time":0.2333,"x":-1.25,"y":-1.78},{"time":0.5,"x":0,"y":0}]},"bone3":{"rotate":[{"angle":0,"curve":"stepped","time":0},{"angle":0,"time":0.1},{"angle":9.95,"time":0.2333},{"angle":0,"time":0.5}],"scale":[{"curve":"stepped","time":0,"x":1,"y":1},{"curve":"stepped","time":0.1,"x":1,"y":1},{"time":0.5,"x":1,"y":1}],"translate":[{"curve":"stepped","time":0,"x":0,"y":0},{"curve":"stepped","time":0.1,"x":0,"y":0},{"curve":"stepped","time":0.2333,"x":0,"y":0},{"time":0.5,"x":0,"y":0}]},"bone4":{"rotate":[{"angle":0,"curve":"stepped","time":0},{"angle":0,"time":0.1},{"angle":9.95,"time":0.2333},{"angle":0,"time":0.5}],"scale":[{"curve":"stepped","time":0,"x":1,"y":1},{"curve":"stepped","time":0.1,"x":1,"y":1},{"time":0.5,"x":1,"y":1}],"translate":[{"curve":"stepped","time":0,"x":0,"y":0},{"curve":"stepped","time":0.1,"x":0,"y":0},{"curve":"stepped","time":0.2333,"x":0,"y":0},{"time":0.5,"x":0,"y":0}]},"bone5":{"rotate":[{"angle":0,"curve":"stepped","time":0},{"angle":0,"time":0.1},{"angle":-17.89,"time":0.2333},{"angle":0,"time":0.5}],"scale":[{"curve":"stepped","time":0,"x":1,"y":1},{"curve":"stepped","time":0.1,"x":1,"y":1},{"time":0.5,"x":1,"y":1}],"translate":[{"curve":"stepped","time":0,"x":0,"y":0},{"time":0.1,"x":0,"y":0},{"time":0.2333,"x":-1.44,"y":-4.22},{"time":0.5,"x":0,"y":0}]},"bone6":{"rotate":[{"angle":0,"curve":"stepped","time":0},{"angle":0,"curve":"stepped","time":0.1},{"angle":0,"curve":"stepped","time":0.2333},{"angle":0,"time":0.5}],"scale":[{"curve":"stepped","time":0,"x":1,"y":1},{"curve":"stepped","time":0.1,"x":1,"y":1},{"time":0.5,"x":1,"y":1}],"translate":[{"curve":"stepped","time":0,"x":0,"y":0},{"time":0.1,"x":0,"y":0},{"time":0.2333,"x":2,"y":0},{"time":0.5,"x":0,"y":0}]},"bone7":{"rotate":[{"angle":0,"curve":"stepped","time":0},{"angle":0,"curve":"stepped","time":0.1},{"angle":0,"curve":"stepped","time":0.2333},{"angle":0,"time":0.5}],"scale":[{"curve":"stepped","time":0,"x":1,"y":1},{"curve":"stepped","time":0.1,"x":1,"y":1},{"time":0.5,"x":1,"y":1}],"translate":[{"curve":"stepped","time":0,"x":0,"y":0},{"time":0.1,"x":0,"y":0},{"time":0.2333,"x":2,"y":0},{"time":0.5,"x":0,"y":0}]},"bone8":{"rotate":[{"angle":0,"time":0},{"angle":2.73,"time":0.1},{"angle":-2.72,"time":0.2333},{"angle":0,"time":0.5}],"scale":[{"curve":"stepped","time":0,"x":1,"y":1},{"curve":"stepped","time":0.1,"x":1,"y":1},{"time":0.5,"x":1,"y":1}],"translate":[{"curve":"stepped","time":0,"x":0,"y":0},{"curve":"stepped","time":0.1,"x":0,"y":0},{"curve":"stepped","time":0.2333,"x":0,"y":0},{"time":0.5,"x":0,"y":0}]},"bone9":{"rotate":[{"angle":0,"time":0},{"angle":2.73,"time":0.1},{"angle":-2.72,"time":0.2333},{"angle":0,"time":0.5}],"scale":[{"curve":"stepped","time":0,"x":1,"y":1},{"curve":"stepped","time":0.1,"x":1,"y":1},{"time":0.5,"x":1,"y":1}],"translate":[{"curve":"stepped","time":0,"x":0,"y":0},{"curve":"stepped","time":0.1,"x":0,"y":0},{"curve":"stepped","time":0.2333,"x":0,"y":0},{"time":0.5,"x":0,"y":0}]},"cheshen":{"rotate":[{"angle":0,"time":0},{"angle":-2.25,"time":0.1},{"angle":4.43,"time":0.2333},{"angle":0,"time":0.5}],"scale":[{"curve":"stepped","time":0,"x":1,"y":1},{"curve":"stepped","time":0.1,"x":1,"y":1},{"time":0.5,"x":1,"y":1}],"translate":[{"time":0,"x":0,"y":0},{"time":0.1,"x":3,"y":0},{"time":0.2333,"x":-3,"y":-2.69},{"time":0.5,"x":0,"y":0}]},"dizuo":{"rotate":[{"angle":0,"curve":"stepped","time":0},{"angle":0,"curve":"stepped","time":0.1},{"angle":0,"curve":"stepped","time":0.2333},{"angle":0,"time":0.5}],"scale":[{"curve":"stepped","time":0,"x":1,"y":1},{"curve":"stepped","time":0.1,"x":1,"y":1},{"time":0.5,"x":1,"y":1}],"translate":[{"curve":"stepped","time":0,"x":0,"y":0},{"curve":"stepped","time":0.1,"x":0,"y":0},{"curve":"stepped","time":0.2333,"x":0,"y":0},{"time":0.5,"x":0,"y":0}]},"root":{"rotate":[{"angle":0,"curve":"stepped","time":0},{"angle":0,"curve":"stepped","time":0.1},{"angle":0,"curve":"stepped","time":0.2333},{"angle":0,"time":0.5}],"scale":[{"curve":"stepped","time":0,"x":1,"y":1},{"time":0.1,"x":1,"y":1},{"time":0.2333,"x":0.972,"y":1},{"time":0.5,"x":1,"y":1}],"translate":[{"time":0,"x":0,"y":0},{"time":0.1,"x":3,"y":0},{"time":0.2333,"x":-5,"y":0},{"time":0.5,"x":0,"y":0}]},"shadow":{"rotate":[{"angle":0,"curve":"stepped","time":0},{"angle":0,"curve":"stepped","time":0.1},{"angle":0,"curve":"stepped","time":0.2333},{"angle":0,"time":0.5}],"scale":[{"curve":"stepped","time":0,"x":1,"y":1},{"time":0.1,"x":1,"y":1},{"time":0.2333,"x":1.035,"y":1.035},{"time":0.5,"x":1,"y":1}],"translate":[{"curve":"stepped","time":0,"x":0,"y":0},{"time":0.1,"x":0,"y":0},{"time":0.2333,"x":-3.01,"y":0},{"time":0.5,"x":0,"y":0}]}},"slots":{"_0007_shitou":{"attachment":[{"name":"_0007_shitou","time":0},{"name":"_0007_shitou","time":0.5}],"color":[{"color":"ffffffff","time":0}]}}},"skill":{"bones":{"bone":{"rotate":[{"angle":0,"time":0},{"angle":-6.25,"time":0.1666},{"angle":-4.89,"time":1.4333},{"angle":0,"curve":"stepped","time":1.5333},{"angle":0,"time":1.8}],"scale":[{"curve":"stepped","time":0,"x":1,"y":1},{"curve":"stepped","time":0.1666,"x":1,"y":1},{"curve":"stepped","time":1.4333,"x":1,"y":1},{"curve":"stepped","time":1.5333,"x":1,"y":1},{"time":1.8,"x":1,"y":1}],"translate":[{"curve":"stepped","time":0,"x":0,"y":0},{"curve":"stepped","time":0.1666,"x":0,"y":0},{"time":1.4333,"x":0,"y":0},{"time":1.5333,"x":-1,"y":0},{"time":1.8,"x":0,"y":0}]},"bone10":{"rotate":[{"angle":0,"time":0},{"angle":7.6,"time":0.1666},{"angle":8.5,"time":1.4333},{"angle":8.17,"time":1.5},{"angle":-19.41,"time":1.5333},{"angle":-16.07,"time":1.6666},{"angle":0,"time":1.8}],"scale":[{"curve":"stepped","time":0,"x":1,"y":1},{"curve":"stepped","time":0.1666,"x":1,"y":1},{"curve":"stepped","time":1.4333,"x":1,"y":1},{"time":1.8,"x":1,"y":1}],"translate":[{"curve":"stepped","time":0,"x":0,"y":0},{"curve":"stepped","time":0.1666,"x":0,"y":0},{"curve":"stepped","time":1.4333,"x":0,"y":0},{"time":1.8,"x":0,"y":0}]},"bone11":{"rotate":[{"angle":0,"curve":"stepped","time":0},{"angle":0,"curve":"stepped","time":0.1666},{"angle":0,"curve":"stepped","time":1.4333},{"angle":0,"time":1.5},{"angle":15.1,"time":1.5333},{"angle":0,"curve":"stepped","time":1.5666},{"angle":0,"time":1.8}],"scale":[{"curve":"stepped","time":0,"x":1,"y":1},{"curve":"stepped","time":0.1666,"x":1,"y":1},{"curve":"stepped","time":1.4333,"x":1,"y":1},{"curve":"stepped","time":1.5,"x":1,"y":1},{"curve":"stepped","time":1.5333,"x":1,"y":1},{"curve":"stepped","time":1.5666,"x":1,"y":1},{"time":1.8,"x":1,"y":1}],"translate":[{"curve":"stepped","time":0,"x":0,"y":0},{"curve":"stepped","time":0.1666,"x":0,"y":0},{"curve":"stepped","time":1.4333,"x":0,"y":0},{"curve":"stepped","time":1.5,"x":0,"y":0},{"time":1.5333,"x":0,"y":0},{"time":1.5666,"x":14.49,"y":-60.26},{"time":1.8,"x":0,"y":0}]},"bone2":{"rotate":[{"angle":0,"time":0},{"angle":-6.25,"time":0.1666},{"angle":-4.89,"time":1.4333},{"angle":0,"curve":"stepped","time":1.5333},{"angle":0,"time":1.8}],"scale":[{"curve":"stepped","time":0,"x":1,"y":1},{"curve":"stepped","time":0.1666,"x":1,"y":1},{"curve":"stepped","time":1.4333,"x":1,"y":1},{"curve":"stepped","time":1.5333,"x":1,"y":1},{"time":1.8,"x":1,"y":1}],"translate":[{"curve":"stepped","time":0,"x":0,"y":0},{"curve":"stepped","time":0.1666,"x":0,"y":0},{"time":1.4333,"x":0,"y":0},{"time":1.5333,"x":-1,"y":0},{"time":1.8,"x":0,"y":0}]},"bone3":{"rotate":[{"angle":0,"time":0},{"angle":6.97,"time":0.1666},{"angle":8.8,"time":1.4333},{"angle":-4.74,"time":1.5333},{"angle":0,"time":1.8}],"scale":[{"curve":"stepped","time":0,"x":1,"y":1},{"curve":"stepped","time":0.1666,"x":1,"y":1},{"curve":"stepped","time":1.4333,"x":1,"y":1},{"curve":"stepped","time":1.5333,"x":1,"y":1},{"time":1.8,"x":1,"y":1}],"translate":[{"curve":"stepped","time":0,"x":0,"y":0},{"curve":"stepped","time":0.1666,"x":0,"y":0},{"curve":"stepped","time":1.4333,"x":0,"y":0},{"curve":"stepped","time":1.5333,"x":0,"y":0},{"time":1.8,"x":0,"y":0}]},"bone4":{"rotate":[{"angle":0,"time":0},{"angle":6.97,"time":0.1666},{"angle":8.8,"time":1.4333},{"angle":-4.74,"time":1.5333},{"angle":0,"time":1.8}],"scale":[{"curve":"stepped","time":0,"x":1,"y":1},{"curve":"stepped","time":0.1666,"x":1,"y":1},{"curve":"stepped","time":1.4333,"x":1,"y":1},{"curve":"stepped","time":1.5333,"x":1,"y":1},{"time":1.8,"x":1,"y":1}],"translate":[{"curve":"stepped","time":0,"x":0,"y":0},{"curve":"stepped","time":0.1666,"x":0,"y":0},{"curve":"stepped","time":1.4333,"x":0,"y":0},{"curve":"stepped","time":1.5333,"x":0,"y":0},{"time":1.8,"x":0,"y":0}]},"bone5":{"rotate":[{"angle":0,"curve":"stepped","time":0},{"angle":0,"curve":"stepped","time":0.1666},{"angle":0,"time":1.4333},{"angle":-5.39,"time":1.5333},{"angle":0,"time":1.8}],"scale":[{"curve":"stepped","time":0,"x":1,"y":1},{"curve":"stepped","time":0.1666,"x":1,"y":1},{"curve":"stepped","time":1.4333,"x":1,"y":1},{"curve":"stepped","time":1.5333,"x":1,"y":1},{"time":1.8,"x":1,"y":1}],"translate":[{"time":0,"x":0,"y":0},{"curve":"stepped","time":0.1666,"x":-0.11,"y":-1.99},{"time":1.4333,"x":-0.11,"y":-1.99},{"curve":"stepped","time":1.5333,"x":0,"y":0},{"time":1.8,"x":0,"y":0}]},"bone6":{"rotate":[{"angle":0,"time":0},{"angle":7.61,"time":0.1666},{"angle":8.06,"time":1.4333},{"angle":-4.53,"time":1.5333},{"angle":0,"time":1.8}],"scale":[{"curve":"stepped","time":0,"x":1,"y":1},{"curve":"stepped","time":0.1666,"x":1,"y":1},{"curve":"stepped","time":1.4333,"x":1,"y":1},{"curve":"stepped","time":1.5333,"x":1,"y":1},{"time":1.8,"x":1,"y":1}],"translate":[{"time":0,"x":0,"y":0},{"curve":"stepped","time":0.1666,"x":-0.05,"y":-0.99},{"time":1.4333,"x":-0.05,"y":-0.99},{"time":1.5333,"x":1,"y":1},{"time":1.8,"x":0,"y":0}]},"bone7":{"rotate":[{"angle":0,"time":0},{"angle":7.61,"time":0.1666},{"angle":8.06,"time":1.4333},{"angle":-4.53,"time":1.5333},{"angle":0,"time":1.8}],"scale":[{"curve":"stepped","time":0,"x":1,"y":1},{"curve":"stepped","time":0.1666,"x":1,"y":1},{"curve":"stepped","time":1.4333,"x":1,"y":1},{"curve":"stepped","time":1.5333,"x":1,"y":1},{"time":1.8,"x":1,"y":1}],"translate":[{"time":0,"x":0,"y":0},{"curve":"stepped","time":0.1666,"x":-0.05,"y":-0.99},{"time":1.4333,"x":-0.05,"y":-0.99},{"time":1.5333,"x":1,"y":1},{"time":1.8,"x":0,"y":0}]},"bone8":{"rotate":[{"angle":0,"time":0},{"angle":7.6,"time":0.1666},{"angle":8.5,"time":1.4333},{"angle":-36.76,"time":1.5},{"angle":-31.1,"time":1.5333},{"angle":-4.51,"time":1.6666},{"angle":0,"time":1.8}],"scale":[{"curve":"stepped","time":0,"x":1,"y":1},{"curve":"stepped","time":0.1666,"x":1,"y":1},{"curve":"stepped","time":1.4333,"x":1,"y":1},{"time":1.8,"x":1,"y":1}],"translate":[{"curve":"stepped","time":0,"x":0,"y":0},{"curve":"stepped","time":0.1666,"x":0,"y":0},{"curve":"stepped","time":1.4333,"x":0,"y":0},{"time":1.8,"x":0,"y":0}]},"bone9":{"rotate":[{"angle":0,"time":0},{"angle":7.6,"time":0.1666},{"angle":8.5,"time":1.4333},{"angle":8.17,"time":1.5},{"angle":-19.41,"time":1.5333},{"angle":-16.07,"time":1.6666},{"angle":0,"time":1.8}],"scale":[{"curve":"stepped","time":0,"x":1,"y":1},{"curve":"stepped","time":0.1666,"x":1,"y":1},{"curve":"stepped","time":1.4333,"x":1,"y":1},{"time":1.8,"x":1,"y":1}],"translate":[{"curve":"stepped","time":0,"x":0,"y":0},{"curve":"stepped","time":0.1666,"x":0,"y":0},{"curve":"stepped","time":1.4333,"x":0,"y":0},{"time":1.8,"x":0,"y":0}]},"cheshen":{"rotate":[{"angle":0,"time":0},{"angle":3.15,"time":0.1666},{"angle":3.6,"time":1.4333},{"angle":-0.8,"time":1.5333},{"angle":0,"time":1.8}],"scale":[{"curve":"stepped","time":0,"x":1,"y":1},{"curve":"stepped","time":0.1666,"x":1,"y":1},{"curve":"stepped","time":1.4333,"x":1,"y":1},{"curve":"stepped","time":1.5333,"x":1,"y":1},{"time":1.8,"x":1,"y":1}],"translate":[{"time":0,"x":0,"y":0},{"time":0.1666,"x":-2,"y":0},{"time":1.4333,"x":-3,"y":0},{"time":1.5333,"x":2,"y":0},{"time":1.8,"x":0,"y":0}]},"dizuo":{"rotate":[{"angle":0,"curve":"stepped","time":0},{"angle":0,"curve":"stepped","time":0.1666},{"angle":0,"curve":"stepped","time":1.4333},{"angle":0,"curve":"stepped","time":1.5333},{"angle":0,"time":1.8}],"scale":[{"curve":"stepped","time":0,"x":1,"y":1},{"curve":"stepped","time":0.1666,"x":1,"y":1},{"curve":"stepped","time":1.4333,"x":1,"y":1},{"curve":"stepped","time":1.5333,"x":1,"y":1},{"time":1.8,"x":1,"y":1}],"translate":[{"curve":"stepped","time":0,"x":0,"y":0},{"curve":"stepped","time":0.1666,"x":0,"y":0},{"time":1.4333,"x":0,"y":0},{"time":1.5333,"x":-1,"y":0},{"time":1.8,"x":0,"y":0}]},"root":{"rotate":[{"angle":0,"curve":"stepped","time":0},{"angle":0,"curve":"stepped","time":0.1666},{"angle":0,"curve":"stepped","time":1.4333},{"angle":0,"curve":"stepped","time":1.5333},{"angle":0,"time":1.8}],"scale":[{"time":0,"x":1,"y":1},{"curve":"stepped","time":0.1666,"x":1,"y":0.976},{"time":1.4333,"x":1,"y":0.976},{"curve":"stepped","time":1.5333,"x":1,"y":1},{"time":1.8,"x":1,"y":1}],"translate":[{"time":0,"x":0,"y":0},{"curve":"stepped","time":0.1666,"x":2,"y":0},{"time":1.4333,"x":2,"y":0},{"curve":"stepped","time":1.5333,"x":0,"y":0},{"time":1.8,"x":0,"y":0}]},"shadow":{"rotate":[{"angle":0,"curve":"stepped","time":0},{"angle":0,"curve":"stepped","time":0.1666},{"angle":0,"curve":"stepped","time":1.4333},{"angle":0,"curve":"stepped","time":1.5333},{"angle":0,"time":1.8}],"scale":[{"time":0,"x":1,"y":1},{"time":0.1666,"x":1.06,"y":1.06},{"time":1.4333,"x":1.047,"y":1.047},{"time":1.5333,"x":0.919,"y":0.919},{"time":1.8,"x":1,"y":1}],"translate":[{"curve":"stepped","time":0,"x":0,"y":0},{"curve":"stepped","time":0.1666,"x":0,"y":0},{"curve":"stepped","time":1.4333,"x":0,"y":0},{"curve":"stepped","time":1.5333,"x":0,"y":0},{"time":1.8,"x":0,"y":0}]}},"slots":{"_0007_shitou":{"attachment":[{"name":"_0007_shitou","time":0},{"name":"shitouying","time":1.5333},{"name":null,"time":1.5666},{"name":null,"time":1.8}],"color":[{"color":"ffffffff","curve":"stepped","time":0},{"color":"ffffffff","curve":"stepped","time":1.5},{"color":"ffffffff","curve":"stepped","time":1.5333},{"color":"ffffffff","time":1.5666},{"color":"ffffff00","time":1.8}]}}},"stand":{"bones":{"bone":{"rotate":[{"angle":0,"curve":"stepped","time":0},{"angle":0,"time":1.3333}],"scale":[{"curve":"stepped","time":0,"x":1,"y":1},{"time":1.3333,"x":1,"y":1}],"translate":[{"time":0,"x":0,"y":0},{"time":0.6666,"x":1,"y":0},{"time":1.3333,"x":0,"y":0}]},"bone10":{"rotate":[{"angle":0,"time":0},{"angle":-1.43,"time":0.3333},{"angle":0.72,"time":1},{"angle":0,"time":1.3333}],"scale":[{"curve":"stepped","time":0,"x":1,"y":1},{"time":1.3333,"x":1,"y":1}],"translate":[{"curve":"stepped","time":0,"x":0,"y":0},{"time":1.3333,"x":0,"y":0}]},"bone11":{"rotate":[{"angle":0,"curve":"stepped","time":0},{"angle":0,"time":1.3333}],"scale":[{"curve":"stepped","time":0,"x":1,"y":1},{"time":1.3333,"x":1,"y":1}],"translate":[{"curve":"stepped","time":0,"x":0,"y":0},{"time":1.3333,"x":0,"y":0}]},"bone2":{"rotate":[{"angle":0,"curve":"stepped","time":0},{"angle":0,"time":1.3333}],"scale":[{"curve":"stepped","time":0,"x":1,"y":1},{"time":1.3333,"x":1,"y":1}],"translate":[{"time":0,"x":0,"y":0},{"time":0.6666,"x":1,"y":0},{"time":1.3333,"x":0,"y":0}]},"bone3":{"rotate":[{"angle":0,"curve":"stepped","time":0},{"angle":0,"time":1.3333}],"scale":[{"curve":"stepped","time":0,"x":1,"y":1},{"time":1.3333,"x":1,"y":1}],"translate":[{"curve":"stepped","time":0,"x":0,"y":0},{"time":1.3333,"x":0,"y":0}]},"bone4":{"rotate":[{"angle":0,"curve":"stepped","time":0},{"angle":0,"time":1.3333}],"scale":[{"curve":"stepped","time":0,"x":1,"y":1},{"time":1.3333,"x":1,"y":1}],"translate":[{"curve":"stepped","time":0,"x":0,"y":0},{"time":1.3333,"x":0,"y":0}]},"bone5":{"rotate":[{"angle":0,"curve":"stepped","time":0},{"angle":0,"time":1.3333}],"scale":[{"curve":"stepped","time":0,"x":1,"y":1},{"time":1.3333,"x":1,"y":1}],"translate":[{"curve":"stepped","time":0,"x":0,"y":0},{"time":1.3333,"x":0,"y":0}]},"bone6":{"rotate":[{"angle":0,"curve":"stepped","time":0},{"angle":0,"time":1.3333}],"scale":[{"curve":"stepped","time":0,"x":1,"y":1},{"time":1.3333,"x":1,"y":1}],"translate":[{"time":0,"x":0,"y":0},{"time":0.6666,"x":0,"y":-0.53},{"time":1.3333,"x":0,"y":0}]},"bone7":{"rotate":[{"angle":0,"curve":"stepped","time":0},{"angle":0,"time":1.3333}],"scale":[{"curve":"stepped","time":0,"x":1,"y":1},{"time":1.3333,"x":1,"y":1}],"translate":[{"time":0,"x":0,"y":0},{"time":0.6666,"x":0,"y":-1},{"time":1.3333,"x":0,"y":0}]},"bone8":{"rotate":[{"angle":0,"time":0},{"angle":-1.43,"time":0.3333},{"angle":0.72,"time":1},{"angle":0,"time":1.3333}],"scale":[{"curve":"stepped","time":0,"x":1,"y":1},{"time":1.3333,"x":1,"y":1}],"translate":[{"curve":"stepped","time":0,"x":0,"y":0},{"time":1.3333,"x":0,"y":0}]},"bone9":{"rotate":[{"angle":0,"time":0},{"angle":-1.43,"time":0.3333},{"angle":0.72,"time":1},{"angle":0,"time":1.3333}],"scale":[{"curve":"stepped","time":0,"x":1,"y":1},{"time":1.3333,"x":1,"y":1}],"translate":[{"curve":"stepped","time":0,"x":0,"y":0},{"time":1.3333,"x":0,"y":0}]},"cheshen":{"rotate":[{"angle":0,"time":0},{"angle":0.44,"time":0.6666},{"angle":0,"time":1.3333}],"scale":[{"curve":"stepped","time":0,"x":1,"y":1},{"time":1.3333,"x":1,"y":1}],"translate":[{"curve":"stepped","time":0,"x":0,"y":0},{"time":1.3333,"x":0,"y":0}]},"dizuo":{"rotate":[{"angle":0,"curve":"stepped","time":0},{"angle":0,"time":1.3333}],"scale":[{"curve":"stepped","time":0,"x":1,"y":1},{"time":1.3333,"x":1,"y":1}],"translate":[{"curve":"stepped","time":0,"x":0,"y":0},{"time":1.3333,"x":0,"y":0}]},"root":{"rotate":[{"angle":0,"curve":"stepped","time":0},{"angle":0,"time":1.3333}],"scale":[{"time":0,"x":1,"y":1},{"time":0.6666,"x":1,"y":0.972},{"time":1.3333,"x":1,"y":1}],"translate":[{"time":0,"x":0,"y":0},{"time":0.6666,"x":-2.31,"y":0},{"time":1.3333,"x":0,"y":0}]},"shadow":{"rotate":[{"angle":0,"curve":"stepped","time":0},{"angle":0,"time":1.3333}],"scale":[{"time":0,"x":1,"y":1},{"time":0.6666,"x":1.085,"y":1.085},{"time":1.3333,"x":1,"y":1}],"translate":[{"curve":"stepped","time":0,"x":0,"y":0},{"curve":"stepped","time":0.6666,"x":0,"y":0},{"time":1.3333,"x":0,"y":0}]}},"drawOrder":[{"time":0},{"time":1.3333}],"slots":{"_0007_shitou":{"attachment":[{"name":"_0007_shitou","time":0},{"name":"_0007_shitou","time":1.3333}],"color":[{"color":"ffffffff","curve":"stepped","time":0},{"color":"ffffffff","time":1.3333}]}}}},"bones":[{"name":"root"},{"name":"bone","parent":"root","x":-49.59,"y":19.63},{"name":"bone2","parent":"root","x":4.51,"y":23.31},{"name":"cheshen","parent":"root","x":7.85,"y":50.7},{"name":"dizuo","parent":"root","x":21.21,"y":25.31},{"name":"shadow","parent":"root","x":-0.31,"y":0.12},{"length":56.8,"name":"bone3","parent":"cheshen","rotation":91.35,"x":16.03,"y":4},{"length":51.58,"name":"bone4","parent":"cheshen","rotation":97.62,"x":59.78,"y":6.34},{"name":"bone5","parent":"cheshen","x":48.09,"y":5.34},{"name":"bone6","parent":"cheshen","x":-47.09,"y":15.36},{"name":"bone7","parent":"cheshen","x":-61.45,"y":-3},{"length":33.34,"name":"bone8","parent":"cheshen","rotation":150.59,"x":18.7,"y":6.67},{"length":31.36,"name":"bone9","parent":"bone8","rotation":2.7,"x":33.34,"y":0.01},{"length":55.52,"name":"bone10","parent":"bone9","rotation":3.6,"x":31.36,"y":0.06},{"name":"bone11","parent":"bone10","x":36.72,"y":-33.36}],"skeleton":{"hash":"hqWicsDy3Cm8++XG+1hM+SOJLJM","height":160.02,"images":"./\u6295\u77f3\u8f66\u5bfc\u51fa/","spine":"2.1.07","width":299.82},"skins":{"default":{"_0000_chetou":{"_0000_chetou":{"height":120,"width":102,"x":-10.35,"y":22.37}},"_0001_cheshen":{"_0001_cheshen":{"height":28,"width":135,"x":-0.33}},"_0002_chewei01":{"_0002_chewei01":{"height":22,"width":48,"x":-2.33,"y":0.66}},"_0003_chewei02":{"_0003_chewei02":{"height":27,"width":63,"x":4.34,"y":-1.33}},"_0004_R-chetou":{"_0004_R-chetou":{"height":60,"rotation":-91.35,"width":61,"x":31.62,"y":23.3}},"_0005_L-chetou":{"_0005_L-chetou":{"height":54,"rotation":-97.62,"width":44,"x":29.49,"y":13.91}},"_0006_F-guo":{"_0006_F-guo":{"height":51,"rotation":-156.9,"width":83,"x":28.36,"y":-3.52}},"_0007_shitou":{"_0007_shitou":{"height":79,"rotation":-156.9,"width":82,"x":-0.35,"y":-3.42},"shitouying":{"height":106,"rotation":-78.78,"width":161,"x":16.31,"y":-49.29}},"_0009_B-gan":{"_0009_B-gan":{"height":26,"rotation":-150.59,"width":38,"x":9.06,"y":-1.79}},"_0010_F-gan":{"_0010_F-gan":{"height":25,"rotation":-153.3,"width":39,"x":10.75,"y":-1.32}},"_0011_RB-chelun":{"_0011_RB-chelun":{"height":39,"width":38,"x":3.33,"y":-0.66}},"_0012_RF-chelun":{"_0012_RF-chelun":{"height":47,"width":46,"x":3.67,"y":-0.33}},"_0013_dizuo":{"_0013_dizuo":{"height":48,"width":180}},"bone10":{"_0008_B-guo":{"height":37,"rotation":-156.9,"width":76,"x":30.19,"y":-10.36}},"shadow":{"shadow":{"height":41,"scaleX":1.998,"scaleY":1.059,"width":150,"x":9.42}}}},"slots":[{"attachment":"shadow","bone":"shadow","name":"shadow"},{"bone":"root","name":"_0014_Background"},{"attachment":"_0013_dizuo","bone":"dizuo","name":"_0013_dizuo"},{"attachment":"_0005_L-chetou","bone":"bone4","name":"_0005_L-chetou"},{"attachment":"_0008_B-guo","bone":"bone10","name":"bone10"},{"attachment":"_0007_shitou","bone":"bone11","name":"_0007_shitou"},{"attachment":"_0006_F-guo","bone":"bone10","name":"_0006_F-guo"},{"attachment":"_0009_B-gan","bone":"bone8","name":"_0009_B-gan"},{"attachment":"_0010_F-gan","bone":"bone9","name":"_0010_F-gan"},{"attachment":"_0003_chewei02","bone":"bone6","name":"_0003_chewei02"},{"attachment":"_0002_chewei01","bone":"bone7","name":"_0002_chewei01"},{"attachment":"_0004_R-chetou","bone":"bone3","name":"_0004_R-chetou"},{"attachment":"_0001_cheshen","bone":"cheshen","name":"_0001_cheshen"},{"attachment":"_0012_RF-chelun","bone":"bone2","name":"_0012_RF-chelun"},{"attachment":"_0011_RB-chelun","bone":"bone","name":"_0011_RB-chelun"},{"attachment":"_0000_chetou","bone":"bone5","name":"_0000_chetou"}]}